Workbook
Name _Hlk138872368: 附註!$A$6

Sheet 資產負債表
A1: 鍍威精密股份有限公司
A2: 資 產 負 債 表
A3: 民國一一三年十二月三十一日及一一二年十二月三十一日
A4: 單位：新台幣元
N5: (未經查核)
C6: 一一三年十二月三十一日 | H6: 一一二年十二月三十一日 | N6: 一一一年十二月三十一日
C7: 金額 | F7: % | H7: 金額 | K7: % | N7: 金額 | Q7: %
A8: 資 產
A9: 流動資產
A10: 現金及約當現金(附註四(一)) | C10: $ | D10: =SUM(BS!C3:C9) -> 5408583 | F10: =ROUND(D10/D$25*100,1) -> 5.1 | H10: $ | I10: 7588579 | K10: =ROUND(I10/I$25*100,1)+0.1 -> 7.7 | N10: $ | O10: 20541058 | Q10: 18.6 | S10: =D10-I10 -> -2179996 | U10: =I10-O10 -> -12952479
A11: 應收票據(附註四(二)) | D11: =BS!C10 -> 4597726 | F11: =ROUND(D11/D$25*100,1) -> 4.4 | I11: 3205259 | K11: =ROUND(I11/I$25*100,1) -> 3.2 | O11: 1441674 | Q11: 1.3 | S11: =I11-D11 -> -1392467 | U11: =O11-I11 -> -1763585
A12: 應收帳款(附註四(三)) | D12: =BS!C11 -> 13444980 | F12: =ROUND(D12/D$25*100,1) -> 12.7 | I12: 7243970 | K12: =ROUND(I12/I$25*100,1) -> 7.2 | O12: 3176716 | Q12: 2.9 | S12: =I12-D12 -> -6201010 | U12: =O12-I12 -> -4067254
A13: 其他應收帳款(附註四(四)) | D13: =BS!C12 -> 1028274 | F13: =ROUND(D13/D$25*100,1) -> 1 | I13: 1197720 | K13: =ROUND(I13/I$25*100,1) -> 1.2 | O13: 1274000 | Q13: 1.2 | S13: =I13-D13 -> 169446 | U13: =O13-I13 -> 76280
A14: 存 貨(附註四(五)) | D14: =BS!C13 -> 2961265 | F14: =ROUND(D14/D$25*100,1) -> 2.8 | I14: 2450275 | K14: =ROUND(I14/I$25*100,1) -> 2.4 | O14: 2136413 | Q14: 1.9 | S14: =I14-D14 -> -510990 | U14: =O14-I14 -> -313862
A15: 預付款項(附註四(六)) | D15: =BS!C15 -> 395327 | F15: =ROUND(D15/D$25*100,1) -> 0.4 | I15: 1354094 | K15: =ROUND(I15/I$25*100,1) -> 1.4 | O15: 2128113 | Q15: 1.9 | S15: =I15-D15 -> 958767 | U15: =O15-I15 -> 774019
A16: 其他流動資產 | D16: =BS!C17 -> 288811 | F16: =ROUND(D16/D$25*100,1) -> 0.3 | I16: 23825 | K16: =ROUND(I16/I$25*100,1) -> 0 | O16: 1186596 | Q16: 1.2 | S16: =I16-D16 -> -264986 | U16: =O16-I16 -> 1162771
A17: 流動資產合計 | D17: =SUM($D$10:$D$16) -> 28124966 | F17: =SUM($F$10:$F$16) -> 26.7 | I17: =SUM($I$10:$I$16) -> 23063722 | K17: =SUM($K$10:$K$16) -> 23.1 | O17: 31884570 | Q17: 29
A18: 非流動資產
A19: 不動產、廠房及設備(附註四(七)) | D19: =BS!C21 -> 54440717 | F19: =ROUND(D19/D$25*100,1) -> 51.6 | I19: 55901057 | K19: =ROUND(I19/I$25*100,1) -> 55.7 | O19: 58976404 | Q19: 53.5 | S19: =I19-D19 -> 1460340 | T19: 折舊 | U19: =O19-I19 -> 3075347
A20: 無形資產(附註四(八)) | D20: =BS!C32+BS!C33 -> 244718 | F20: =ROUND(D20/D$25*100,1) -> 0.2 | I20: 120347 | K20: =ROUND(I20/I$25*100,1) -> 0.1 | O20: 221615 | Q20: 0.2
A21: 存出保證金(附註四(九)) | D21: =BS!C35 -> 16825600 | F21: =ROUND(D21/D$25*100,1) -> 15.9 | I21: 16825600 | K21: =ROUND(I21/I$25*100,1) -> 16.8 | O21: 16810600 | Q21: 15.2 | S21: =I21-D21 -> 0 | U21: =O21-I21 -> -15000
A22: 預付設備款(附註四(十)) | D22: =BS!C36 -> 1596848 | F22: =ROUND(D22/D$25*100,1) -> 1.5 | I22: 0 | K22: 0
A23: 遞延所得稅資產(附註四(十八)) | D23: =BS!C37 -> 4314920 | F23: =ROUND(D23/D$25*100,1) -> 4.1 | I23: 4361682 | K23: =ROUND(I23/I$25*100,1) -> 4.3 | O23: 2361682 | Q23: 2.1 | S23: =I23-D23 -> 46762 | U23: =O23-I23 -> -2000000
A24: 非流動資產合計 | D24: =SUM(D19:D23) -> 77422803 | F24: =SUM(F19:F23) -> 73.3 | I24: =SUM(I19:I23) -> 77208686 | K24: =SUM(K19:K23) -> 76.9 | O24: 78370301 | Q24: 71
A25: 資 產 總 計 | C25: $ | D25: =$D$17+$D$24 -> 105547769 | F25: =$F$17+$F$24 -> 100 | H25: $ | I25: =$I$17+$I$24 -> 100272408 | K25: =$K$17+$K$24 -> 100 | N25: $ | O25: 110254871 | Q25: 100
A27: 負 債 及 權 益
A28: 流動負債
A29: 應付票據(附註四(十一)) | C29: $ | D29: =BS!G5 -> 311654 | F29: =ROUND(D29/D$25*100,1) -> 0.3 | H29: $ | I29: 2455819 | K29: =ROUND(I29/I$25*100,1) -> 2.4 | O29: 11960991 | Q29: 10.8 | S29: =D29-I29 -> -2144165 | U29: =I29-O29 -> -9505172
A30: 應付帳款(附註四(十二)) | D30: =BS!G6 -> 4339539 | F30: =ROUND(D30/D$25*100,1) -> 4.1 | I30: 5966576 | K30: =ROUND(I30/I$25*100,1)-0.1 -> 5.9 | N30: $ | O30: 3459200 | Q30: 3.1 | S30: =D30-I30 -> -1627037 | U30: =I30-O30 -> 2507376
A31: 其他應付款(附註四(十三)) | D31: =BS!G7 -> 11112008 | F31: =ROUND(D31/D$25*100,1) -> 10.5 | I31: 8603814 | K31: =ROUND(I31/I$25*100,1) -> 8.6 | O31: 8369093 | Q31: 7.6 | S31: =D31-I31 -> 2508194 | U31: =I31-O31 -> 234721
A32: 預收貨款 | D32: 1202 | F32: =ROUND(D32/D$25*100,1) -> 0 | I32: 0 | K32: 0 | S32: =D32-I32 -> 1202 | U32: =I32-O32 -> 0
A33: 其他流動負債(附註四(十三)) | D33: =BS!G14 -> 207418 | F33: =ROUND(D33/D$25*100,1) -> 0.2 | I33: 153246 | K33: =ROUND(I33/I$25*100,1) -> 0.2 | O33: 111363 | Q33: 0.1 | S33: =D33-I33 -> 54172 | U33: =I33-O33 -> 41883
A34: 一年內到期長期借款(附註四(十四)) | D34: =BS!G3 -> 6701448 | F34: =ROUND(D34/D$25*100,1) -> 6.3 | I34: 2594200 | K34: =ROUND(I34/I$25*100,1) -> 2.6 | O34: 2979507 | Q34: 2.7 | S34: =D34-I34 -> 4107248 | U34: =I34-O34 -> -385307
A35: 流動負債合計 | D35: =SUM(D29:D34) -> 22673269 | F35: =SUM(F29:F34) -> 21.4 | I35: =SUM(I29:I34) -> 19773655 | K35: =SUM(K29:K34) -> 19.7 | O35: 26880154 | Q35: 24.3
A36: 非流動負債
A37: 長期借款(附註四(十四)) | D37: =BS!G17 -> 21601165 | F37: =ROUND(D37/D$25*100,1) -> 20.5 | I37: 19412464 | K37: =ROUND(I37/I$25*100,1)-0.1 -> 19.3 | O37: 11421445 | Q37: 10.4 | S37: =D37-I37 -> 2188701 | U37: =I37-O37 -> 7991019
A38: 非流動負債合計 | D38: =SUM(D37:D37) -> 21601165 | F38: =SUM(F37:F37) -> 20.5 | I38: =SUM(I37:I37) -> 19412464 | K38: =SUM(K37:K37) -> 19.3 | O38: 11421445 | Q38: 10.4
A39: 負債總計 | D39: =D35+D38 -> 44274434 | F39: =F35+F38 -> 41.9 | I39: =I35+I38 -> 39186119 | K39: =K35+K38 -> 39 | O39: 38301599 | Q39: 34.7
A41: 權 益
A42: 股 本(附註四(十五)) | D42: =BS!H20 -> 90000000 | F42: =ROUND(D42/D$25*100,1) -> 85.3 | I42: 90000000 | K42: =ROUND(I42/I$25*100,1) -> 89.8 | O42: 80000000 | Q42: 72.6 | S42: =D42-I42 -> 0 | U42: =I42-O42 -> 10000000
A43: 資本公積(附註四(十六)) | D43: =BS!H22 -> 1400000 | F43: =ROUND(D43/$D$25*100,1) -> 1.3 | I43: 1400000 | K43: =ROUND(I43/$I$25*100,1) -> 1.4 | O43: 1400000 | Q43: 1.3
A44: 保留盈餘(附註四(十七))
A45: 待彌補虧損(附註四(十八)) | D45: =BS!G25+BS!G26 -> -30126665 | F45: =ROUND(D45/D$25*100,1) -> -28.5 | I45: -30313711 | K45: =ROUND(I45/I$25*100,1) -> -30.2 | M45: ( | O45: -9446728 | P45: )( | Q45: -8.6 | R45: )
A46: 權益總計 | D46: =SUM(D42:D45) -> 61273335 | F46: =SUM(F42:F45) -> 58.1 | I46: =SUM(I42:I45) -> 61086289 | K46: =SUM(K42:K45) -> 61 | O46: 71953272 | Q46: 65.3
A47: 負債及權益總計 | C47: $ | D47: =D39+D46 -> 105547769 | F47: =F39+F46 -> 100 | H47: $ | I47: =I39+I46 -> 100272408 | K47: =K39+K46 -> 100 | N47: $ | O47: 110254871 | Q47: 100
A50: (請參閱後附財務報表附註)
A52: 負 責 人： 經 理 人： 主辦會計：

Sheet 損益表
A1: =資產負債表!A1 -> 鍍威精密股份有限公司
A2: 綜 合 損 益 表
A3: 民國一一三年一月一日至十二月三十一日
A4: 及一一二年一月一日至十二月三十一日
A6: 單位：新台幣元
C7: 一一三年度 | H7: 一一二年度
A9: 項目 | C9: 金額 | F9: % | H9: 金額 | K9: %
A10: 營業收入 | C10: $ | D10: =IS!D6 -> 52599315 | F10: =D10/D$10*100 -> 100 | H10: $ | I10: 28721719 | K10: =I10/I$10*100 -> 100
A11: 營業成本(附註四(十九)) | D11: =-IS!D7 -> -33039914 | F11: =ROUND(D11/D$10*100,2) -> -62.81 | I11: -34288954 | K11: =ROUND(I11/I$10*100,2) -> -119.38
A12: 營業毛利(損) | D12: =D10+D11 -> 19559401 | F12: =F10+F11 -> 37.19 | I12: =I10+I11 -> -5567235 | K12: =K10+K11 -> -19.38
A13: 營業費用 | D13: =-IS!D43 -> -19136173 | F13: =ROUND(D13/D$10*100,2) -> -36.38 | I13: -16891577 | K13: =ROUND(I13/I$10*100,2) -> -58.81
A14: 營業淨利(損) | D14: =D12+D13 -> 423228 | F14: =F12+F13 -> 0.81 | I14: =I12+I13 -> -22458812 | K14: =K12+K13 -> -78.19
A15: 營業外收益及費損
A16: 利息收入 | D16: =IS!C67 -> 160806 | F16: =ROUND(D16/D$10*100,2) -> 0.31 | I16: 185761 | K16: =ROUND(I16/I$10*100,2) -> 0.65
A17: 租金收入
A18: 股利收入
A19: 利息費用
A20: 採用權益法認列之投資損益
A21: 利息費用 | D21: =-IS!C71 -> -704142 | F21: =ROUND(D21/D$10*100,2) -> -1.34 | I21: -372259 | K21: =ROUND(I21/I$10*100,2) -> -1.3
A22: 處分投資損益 | D22: 0 | F22: =ROUND(D22/D$10*100,2) -> 0 | I22: 0 | K22: =ROUND(I22/I$10*100,2) -> 0
A23: 處分不動產、廠房及設備損益 | D23: 0 | F23: =ROUND(D23/D$10*100,2) -> 0 | I23: 0 | K23: =ROUND(I23/I$10*100,2) -> 0
A24: 其他營業外收益及費損 | D24: =IS!C68+IS!C69 -> 353916 | F24: =ROUND(D24/D$10*100,2) -> 0.67 | I24: -221673 | K24: =ROUND(I24/I$10*100,2) -> -0.77
A25: 營業外收益及費損合計 | D25: =SUM(D16:D24) -> -189420 | F25: =SUM(F16:F24) -> -0.36 | I25: =SUM(I16:I24) -> -408171 | K25: =SUM(K16:K24) -> -1.42
A26: 稅前淨利(損) | D26: =D14+D25 -> 233808 | F26: =F14+F25 -> 0.45 | I26: =I14+I25 -> -22866983 | K26: =K14+K25 -> -79.61
A27: 所得稅利益(費用)(附註四(十八)) | D27: =-IS!C73 -> -46762 | F27: =ROUND(D27/D$10*100,2) -> -0.09 | I27: 2000000 | K27: =ROUND(I27/I$10*100,2) -> 6.96
A28: 本期稅後淨損 | D28: =D26+D27 -> 187046 | F28: =F26+F27 -> 0.36 | I28: =I26+I27 -> -20866983 | K28: =K26+K27 -> -72.65
A29: 本期其他綜合損益 | D29: 0 | F29: 0 | I29: 0 | K29: 0
A30: 本期綜合損益總額 | C30: $ | D30: =D28 -> 187046 | F30: =F28 -> 0.36 | H30: $ | I30: =I28 -> -20866983 | K30: =K28 -> -72.65
A31: (請參閱後附財務報表附註)
A33: 負 責 人： | D33: 經理人： | I33: 主辦會計：

Sheet 股東變動表
A1: =損益表!A1 -> 鍍威精密股份有限公司
A2: 權 益 變 動 表
A3: =損益表!A3 -> 民國一一三年一月一日至十二月三十一日
A4: =損益表!A4 -> 及一一二年一月一日至十二月三十一日
A5: 單位：新台幣元
I6: 保留盈餘
C7: 股本 | F7: 資本公積 | I7: 法定盈餘 公積 | L7: 未分配盈餘 | O7: 權益總計
A8: 一一二年一月一日餘額 | C8: $ | D8: 80000000 | F8: $ | G8: 1400000 | I8: $ | J8: 0 | L8: $ | M8: -9446728 | O8: $ | P8: 71953272
A9: 現金增資(附註四(十五)) | D9: 10000000 | G9: 0 | J9: 0 | M9: 0 | P9: 10000000
A10: 盈餘指撥及分配
A11: 法定盈餘公積 | D11: 0 | G11: 0 | J11: 0 | M11: 0 | P11: 0
A12: 現金股利 | D12: 0 | G12: 0 | J12: 0 | P12: 0
A13: 本期稅後淨損 | D13: 0 | G13: 0 | J13: 0 | M13: =損益表!I28 -> -20866983 | P13: =M13 -> -20866983
A14: 一一二年十二月三十一日餘額 | C14: $ | D14: 90000000 | F14: $ | G14: 1400000 | I14: $ | J14: 0 | L14: $ | M14: =SUM(M8:M13) -> -30313711 | O14: $ | P14: =SUM(P8:P13) -> 61086289
A15: 一一三年一月一日餘額 | C15: $ | D15: =D14 -> 90000000 | F15: $ | G15: =G14 -> 1400000 | I15: $ | J15: 0 | L15: $ | M15: =M14 -> -30313711 | O15: $ | P15: =SUM(D15:N15) -> 61086289
A16: 現金增資(附註四(十五)) | D16: 0 | G16: 0 | J16: 0 | M16: 0 | P16: =SUM(D16:N16) -> 0
A17: 盈餘指撥及分配
A18: 法定盈餘公積 | D18: 0 | G18: 0 | J18: 0 | M18: 0 | P18: =SUM(D18:N18) -> 0
A19: 現金股利 | D19: 0 | G19: 0 | J19: 0 | P19: =SUM(D19:N19) -> 0
A20: 本期稅後淨利 | D20: 0 | G20: 0 | J20: 0 | M20: =損益表!D28 -> 187046 | P20: =SUM(D20:N20) -> 187046
A21: 一一三年十二月三十一日餘額 | C21: $ | D21: =SUM(D15:D20) -> 90000000 | F21: $ | G21: =SUM(G15:G20) -> 1400000 | I21: $ | J21: =SUM(J15:J20) -> 0 | L21: $ | M21: =M15-M19+M20 -> -30126665 | O21: $ | P21: =P15-P19+P20+P16 -> 61273335
A24: (請參閱後附財務報表附註)
A27: 負 責 人： | F27: 經理人： | M27: 主辦會計：

Sheet 現金流量表
A1: =資產負債表!A1 -> 鍍威精密股份有限公司
A2: 現金流量表
A3: =損益表!A3 -> 民國一一三年一月一日至十二月三十一日
A4: =損益表!A4 -> 及一一二年一月一日至十二月三十一日
A6: 單位：新台幣元
C7: =損益表!C7 -> 一一三年度 | H7: 一一二年度
A9: 營業活動之現金流量
A10: 本期稅前淨利(損) | C10: $ | D10: =損益表!D26 -> 233808 | H10: $ | I10: =損益表!I26 -> -22866983
A11: 調整項目：
A12: 收益費損項目
A13: 利息收入 | D13: =-損益表!D16 -> -160806 | I13: =-損益表!I16 -> -185761
A14: 利息費用 | D14: =-損益表!D21 -> 704142 | I14: =-損益表!I21 -> 372259
A15: 折舊費用 | D15: =-'調節表 '!D53 -> 3848594 | I15: =-'調節表 '!E53 -> 7976172
A16: 攤銷費用 | D16: =-'調節表 '!D84 -> 51107 | I16: =-'調節表 '!E84 -> 101268
A17: 處分不動產、廠房及設備損益
A18: 與營業活動相關之流動資產/負債變動數
A19: 應收票據增加 | D19: =資產負債表!S11 -> -1392467 | I19: =資產負債表!U11 -> -1763585
A20: 應收帳款增加 | D20: =資產負債表!S12 -> -6201010 | I20: =資產負債表!U12 -> -4067254
A21: 其他應收款減少 | D21: =資產負債表!S13 -> 169446 | I21: =資產負債表!U13 -> 76280
A22: 存貨增加 | D22: =資產負債表!S14 -> -510990 | I22: =資產負債表!U14 -> -313862
A23: 預付款項減少 | D23: =資產負債表!S15 -> 958767 | I23: =資產負債表!U15 -> 774019
A24: 其他流動資產(增加)減少 | D24: =資產負債表!S16 -> -264986 | I24: =資產負債表!U16 -> 1162771
A25: 應付票據減少 | D25: =資產負債表!S29 -> -2144165 | I25: =資產負債表!U29 -> -9505172
A26: 應付帳款(減少)增加 | D26: =資產負債表!S30 -> -1627037 | I26: =資產負債表!U30 -> 2507376
A27: 其他應付款增加 | D27: ='調節表 '!D5 -> 2493008 | I27: ='調節表 '!E5 -> 231030
A28: 預收款項增加 | D28: =資產負債表!S32 -> 1202 | I28: 0
A29: 其他流動負債增加 | D29: =資產負債表!S33 -> 54172 | I29: =資產負債表!I33-資產負債表!O33 -> 41883
A30: 營運產生之現金 | D30: =SUM(D10:D29) -> -3787215 | I30: =SUM(I10:I29) -> -25459559
A31: 支付之利息 | D31: =-'調節表 '!D11 -> -688956 | I31: =-'調節表 '!E11 -> -368568
A32: 支付之所得稅 | D32: 0 | I32: 0
A33: 收取之利息 | D33: =損益表!D16 -> 160806 | I33: =損益表!I16 -> 185761
A34: 收取之股利
A35: 營業活動之淨現金流出 | D35: =SUM(D30:D33) -> -4315365 | I35: =SUM(I30:I33) -> -25642366
A37: 投資活動之現金流量
A38: 取得不動產、廠房及設備 | D38: =-'調節表 '!D50 -> -2388254 | I38: =-'調節表 '!E50 -> -4900825
A39: 處分不動產、廠房及設備價款
A40: 取得無形資產 | D40: =-'調節表 '!D83 -> -175478 | I40: 0
A41: 預付設備款增加 | D41: =-'調節表 '!D79 -> -1596848 | I41: 0
A42: 存出保證金增加 | D42: =資產負債表!S21 -> 0 | I42: =資產負債表!U21 -> -15000
A43: 投資活動之淨現金流出 | D43: =SUM(D38:D42) -> -4160580 | I43: =SUM(I38:I42) -> -4915825
A45: 籌資活動之現金流量
A46: 短期借款增加(減少) | D46: =資產負債表!S34 -> 4107248 | I46: =資產負債表!U34 -> -385307
A47: 長期借款增加 | D47: =資產負債表!S37 -> 2188701 | I47: =資產負債表!U37 -> 7991019
A48: 發放現金股利 | I48: 0
A49: 現金增資 | D49: 0 | I49: =資產負債表!U42 -> 10000000
A50: 資本公積溢價 | D50: 0 | I50: 0
A51: 籌資活動之淨現金流入 | D51: =SUM(D46:D50) -> 6295949 | I51: =SUM(I46:I50) -> 17605712
A53: 本期現金及約當現金減少數 | D53: =D35+D43+D51 -> -2179996 | I53: =I35+I43+I51 -> -12952479 | K53: 113年 | L53: 112年
A54: 期初現金及約當現金餘額 | D54: =資產負債表!I10 -> 7588579 | I54: 20541058 | K54: =資產負債表!D10 -> 5408583 | L54: =資產負債表!I10 -> 7588579
A55: 期末現金及約當現金餘額 | C55: $ | D55: =SUM(D53:D54) -> 5408583 | H55: $ | I55: =SUM(I53:I54) -> 7588579 | K55: =D55-K54 -> 0 | L55: =I55-L54 -> 0
A56: (請參閱後附財務報表附註)
A57: 負責人： 經理人： 主辦會計：

Sheet 調節表 
A2: 1 | D2: 113年度 | E2: 112年度
B3: 期初應付費用 | D3: =E4 -> 8592311 | E3: 8361281
B4: 期末應付費用 | D4: =BS!G7-D10 -> 11085319 | E4: 8592311
B5: 應付費用付現數 | C5: A | D5: =D4-D3 -> 2493008 | E5: =E4-E3 -> 231030
D7: =$D$13 -> 113年度 | E7: =$E$13 -> 112年度
A8: 2 | B8: 期初應付利息 | D8: =E10 -> 11503 | E8: 7812
B9: 本期利息費用 | C9: D | D9: =-損益表!D21 -> 704142 | E9: 372259
B10: 期末應付利息 | D10: 26689 | E10: 11503
B11: 利息付現數 | C11: E | D11: =D8+D9-D10 -> 688956 | E11: =E8+E9-E10 -> 368568
D13: =D2 -> 113年度 | E13: =E2 -> 112年度 | H13: 支付所得稅 | I13: 111 | J13: 110 | K13: 109 | L13: 108
A14: 3 | B14: 期初應付所得稅 | D14: =E18 -> 0 | E14: 0 | H14: 暫繳
B15: 期初應退所得稅 | D15: =E19 -> 0 | E15: 0
B16: 期初遞延所得稅負債 | E16: 0 | H16: 未分配
B17: 本期所得稅費用 | C17: B | D17: 0 | E17: 0 | H17: 補稅
B18: 期末應付所得稅 | D18: 0 | E18: 0 | H18: 108營所
B19: 期末應退所得稅 | D19: 0 | E19: 0
B20: 本期支付所得稅 | C20: C | D20: =D14-D15+D17-D18+D19 -> 0 | E20: 0 | H20: 收到所得稅
H21: 淨支付 | I21: =I19-I20 -> 0 | J21: =J19-J20 -> 0
D22: =D7 -> 113年度 | E22: =E7 -> 112年度
B23: 期初其他應付款
B24: 期初應付利息
B25: 期初小計
B26: 期末其他應付款
B27: 期末應付利息
B28: 期末小計
B29: 本期變動數 | C29: h.
D31: =D22 -> 113年度 | E31: =E22 -> 112年度
B32: 期初其他流動資產
B33: 期初應收利息
B34: 期初小計
B35: 期末其他流動資產
B36: 期末應收利息
B37: 期末小計
B38: 本期變動數 | C38: e.
D40: =D31 -> 113年度 | E40: =E31 -> 112年度
B41: 期初無形資產 | D41: =D21 -> 0
B42: 預付未攤銷費用重分類
B43: 本期增添
B44: 利息資本化
B45: 攤提費用
B47: 期末無形資產 | C47: b1. | D47: =SUM(D41:D45) -> 0
D48: =D40 -> 113年度 | E48: =E40 -> 112年度
A49: 4 | B49: 期初固定資產 | D49: =E56 -> 55901057 | E49: 58976404
B50: 購置固定資產 | C50: F | D50: 2388254 | E50: 4900825
B51: 重分類
B52: 出售價款
B53: 折舊費用 | C53: G | D53: -3848594 | E53: -7976172
B54: 處分固定資產利益
B55: 處分固定資產損失
B56: 期末固定資產 | D56: =SUM(D49:D55) -> 54440717 | E56: =E49+E50+E51+E53 -> 55901057
D58: =$D$13 -> 113年度 | E58: =$E$13 -> 112年度
A59: 5 | B59: 期初未攤銷費用 | D59: =E63 -> 0 | E59: 0
B60: 本期新增 | C60: H | D60: 0 | E60: 0
B61: 攤銷費用 | C61: I | D61: 0 | E61: 0
B62: 重分類 | E62: 0
B63: 期末未攤銷費用 | D63: =SUM(D59:D61) -> 0 | E63: =E59+E60+E61+E62 -> 0
D64: =$D$13 -> 113年度 | E64: =$E$13 -> 112年度
A65: 6 | B65: 期初存出保證金 | D65: =E68 -> 16825600 | E65: 16810600
B66: 本期新增 | C66: J | D66: 0 | E66: 0
B67: 本期減少 | C67: K | D67: 0 | E67: 15000
B68: 期末存出保證金 | D68: =SUM(D65:D67) -> 16825600 | E68: =E65+E66+E67 -> 16825600
A70: 7 | D70: =D48 -> 113年度 | E70: =E48 -> 112年度
B71: 期初其他非流動資產 | D71: 0 | E71: 0
B72: 期初預付設備款 | D72: 0 | E72: 0
B73: 期初小計 | D73: =D71+D72 -> 0 | E73: =E71+E72 -> 0
B75: 期末其他非流動資產 | E75: 0
B76: 期末預付設備款 | D76: 1596848 | E76: 0
B77: 期末小計 | D77: =D75+D76 -> 1596848 | E77: =E75+E76 -> 0
B79: 本期變動數 | C79: k. | D79: =D77-D73 -> 1596848 | E79: =E77-E73 -> 0
A81: 8 | D81: 112年度 | E81: 111年度
B82: 期初無形資產 | D82: =E86 -> 120347 | E82: 221615
B83: 本期增添 | D83: 175478 | E83: 0
B84: 攤提費用 | D84: -51107 | E84: -101268
B85: 重分類 | E85: 0
B86: 期末無形資產 | C86: b1. | D86: =SUM(D82:D84) -> 244718 | E86: =SUM(E82:E85) -> 120347

Sheet 附註
A1: (一)現金及約當現金
C2: 一一三年底 | F2: 一一二年底
A3: 庫存現金 | C3: $ | D3: =BS!C3 -> 36210 | F3: $ | G3: =TB!C4 -> 36270
A4: 銀行存款 | D4: =SUM(BS!C4:C9) -> 5372373 | G4: =SUM(TB!C6:C11) -> 7552309
A5: 合 計 | C5: $ | D5: =SUM(D3:D4) -> 5408583 | F5: $ | G5: =G3+G4 -> 7588579
A6: (二)應收票據
C7: =C2 -> 一一三年底 | F7: =F2 -> 一一二年底
A8: 應收票據 | C8: $ | D8: =BS!C10 -> 4597726 | F8: $ | G8: =TB!C14 -> 3205259
A9: 合 計 | C9: $ | D9: =D8 -> 4597726 | F9: $ | G9: =G8 -> 3205259
A10: (三)應收帳款
C11: =C2 -> 一一三年底 | F11: =F2 -> 一一二年底
A12: 應收帳款 | C12: $ | D12: =BS!C11 -> 13444980 | F12: $ | G12: =TB!C16 -> 7243970
A13: 合 計 | C13: $ | D13: =SUM(D12:D12) -> 13444980 | F13: $ | G13: =G12 -> 7243970
A15: (四)其他應收帳款
C16: =C2 -> 一一三年底 | F16: =F2 -> 一一二年底
A17: 其他應收帳款 | C17: $ | D17: =BS!C12 -> 1028274 | F17: $ | G17: =TB!C22 -> 1197720
A18: 合 計 | C18: $ | D18: =SUM(D17:D17) -> 1028274 | F18: $ | G18: =G17 -> 1197720
A20: (五)存貨
C21: =C2 -> 一一三年底 | F21: =F2 -> 一一二年底
A22: 原料存貨 | C22: $ | D22: =BS!C13 -> 2961265 | F22: $ | G22: =TB!C27 -> 2450275
A23: 合計 | C23: $ | D23: =SUM(D22:D22) -> 2961265 | F23: $ | G23: =G22 -> 2450275
A26: (六)預付款項
C27: =C2 -> 一一三年底 | F27: =F2 -> 一一二年底
A28: 預付費用 | C28: $ | D28: =TB!I33 -> 395327 | F28: $ | G28: =TB!C33 -> 827848
A29: 留抵稅額 | D29: – | G29: =TB!C37 -> 509358
A30: 進項稅額 | D30: – | G30: =TB!C36 -> 16888
A31: 合 計 | C31: $ | D31: =D28 -> 395327 | F31: $ | G31: =G28+G30+G29 -> 1354094
A35: (八)無形資產
C36: =C2 -> 一一三年底 | F36: =F2 -> 一一二年底
A37: 無形資產 | C37: $ | D37: =TB!I79 -> 479288 | F37: $ | G37: =TB!C79 -> 303810
A38: 累計攤折 | D38: =-TB!J80 -> -234570 | G38: =-TB!D80 -> -183463
A39: 合計 | C39: $ | D39: =D37+D38 -> 244718 | F39: $ | G39: =G37+G38 -> 120347
A42: (九)存出保證金
C43: =C2 -> 一一三年底 | F43: =F2 -> 一一二年底
A44: 存出保證金 | C44: $ | D44: =BS!C35 -> 16825600 | F44: $ | G44: =TB!C100 -> 16825600
A45: 合 計 | C45: $ | D45: =SUM(D44:D44) -> 16825600 | F45: $ | G45: =G44 -> 16825600
A47: (十)預付設備款
C48: =C2 -> 一一三年底 | F48: =F2 -> 一一二年底
A49: 預付設備款 | C49: $ | D49: =BS!C36 -> 1596848 | F49: $ | G49: –
A50: 合 計 | C50: $ | D50: =D49 -> 1596848 | F50: $ | G50: =G49 -> –
A52: (十一)應付票據
C53: =C2 -> 一一三年底 | F53: =F2 -> 一一二年底
A54: 應付票據 | C54: $ | D54: =BS!G5 -> 311654 | F54: $ | G54: 2455819
A55: 合 計 | C55: $ | D55: =D54 -> 311654 | F55: $ | G55: =G54 -> 2455819
A57: (十二)應付帳款
C58: =C2 -> 一一三年底 | F58: =F2 -> 一一二年底
A59: 應付帳款 | C59: $ | D59: =BS!G6 -> 4339539 | F59: $ | G59: =TB!D117 -> 5966576
A60: 合 計 | C60: $ | D60: =D59 -> 4339539 | F60: $ | G60: =G59 -> 5966576
A62: (十三)其他應付款
C63: =C2 -> 一一三年底 | F63: =F2 -> 一一二年底
A64: 其他應付費用 | C64: $ | D64: =BS!G8+BS!G10+BS!G11-D66-D67 -> 7663138 | F64: $ | G64: 6571432
A65: 應付薪資 | D65: =BS!G9 -> 3012320 | G65: 1673855
A66: 應付勞健保 | D66: 298109 | G66: 234524
A67: 應付勞退 | D67: 138441 | G67: 124003
A68: 合計 | C68: $ | D68: =SUM(D64:D67) -> 11112008 | F68: $ | G68: =SUM(G64:G67) -> 8603814
A70: (十三)其他流動負債
C71: =C2 -> 一一三年底 | F71: =F2 -> 一一二年底
A72: 代收款 | C72: $ | D72: =BS!G14 -> 207418 | F72: $ | G72: 111363
A73: 合 計 | C73: $ | D73: =D72 -> 207418 | F73: $ | G73: =G72 -> 111363
A75: (十四)銀行借款
C76: =C2 -> 一一三年底 | F76: =F2 -> 一一二年底
A77: 中長期擔保借款 | C77: $ | D77: =BS!G4+BS!G17 -> 28302613 | F77: $ | G77: =TB!D112+TB!D153 -> 22006664
A78: 減：一年內到期部份 | D78: =-BS!G4 -> -6701448 | G78: =-TB!D112 -> -2594200
A79: 合計 | C79: $ | D79: =SUM(D77:D78) -> 21601165 | F79: $ | G79: =G77+G78 -> 19412464
A80: 借款利率 | D80: 2.22~2.575% | G80: 2.095%~2.45%
A82: (十五)資本公積
C83: =C2 -> 一一三年底 | F83: =F2 -> 一一二年底
A84: 發行股本溢價 | C84: $ | D84: =TB!J175 -> 1400000 | F84: $ | G84: =TB!D175 -> 1400000
A85: 合計 | C85: $ | D85: =SUM(D84:D84) -> 1400000 | F85: $ | G85: =G84 -> 1400000
A89: 六、質抵押之資產：
C90: =C2 -> 一一三年底 | F90: =F2 -> 一一二年底
A91: 土地 | C91: $ | D91: =[1]TB!I61 -> 22582000 | F91: $ | G91: 22582000
A92: 建築物 | D92: =[1]TB!I65-[1]TB!J66 -> 8656583 | G92: 8841421
A93: 合計 | C93: $ | D93: =D91+D92 -> 31238583 | F93: $ | G93: =G91+G92 -> 31423421
C95: 一一二年底 | F95: 一一一年底
A96: 營業收入 | C96: $ | D96: =[2]當期損益表!C4 -> 218352933 | F96: $ | G96: 146907596
A97: 其他營業收入 | D97: =[2]當期損益表!C5 -> 3571428 | G97: 3600000
A98: 減：銷貨退回 | C98: ( | D98: =[2]當期損益表!C6 -> -9305 | E98: ) | G98: 49419
A99: 減：銷貨折讓 | C99: ( | D99: =[2]當期損益表!C7 -> -293769 | E99: ) | F99: ( | G99: 73963
A100: 合 計 | C100: $ | D100: =SUM(D96:D99) -> 221621287 | F100: $ | G100: 150384214
A102: (二)與關係人間之重大交易事項 | H102: )
C103: 一一二年底 | F103: 一一一年底
A104: 其他應收款 | C104: $ | F104: $
A105: 其他應付款
A106: 合 計 | C106: $ | F106: $
K109: (九)所 得 稅
K110: 1. 所得稅費用組成如下：
M111: =C2 -> 一一三年底 | P111: =F2 -> 一一二年底
K112: 當期所得稅費用 | M112: $ | N112: 46762 | P112: $ | Q112: –
K113: 遞延所稅費用(利益) | N113: – | Q113: -2000000
K114: 所得稅(利益)費用合計 | M114: $ | N114: =N112 -> 46762 | P114: $ | Q114: =Q113 -> -2000000
K115: 2. 本期所得稅負債(資產)調節如下：
M116: =C2 -> 一一三年底 | P116: =F2 -> 一一二年底
K117: 稅前淨利 | M117: $ | N117: 233808 | P117: $ | Q117: -22866983
K118: 加：依稅法規定調整數 | N118: – | Q118: 893234
K119: 減：前十年核定虧損本年度扣除額 | N119: =-N117 -> -233808 | Q119: –
K120: 課稅所得額 | N120: – | Q120: =Q117+Q118 -> -21973749
K121: 所得稅率 | N121: 20% | Q121: 20%
K122: 當期所得稅費用 | N122: – | Q122: –
K123: 加：未分配盈餘加徵5% | N123: – | Q123: –
...

Sheet 附註用人費用
B1: 功能別 | C1: 一一三年度 | F1: 一一二年度
C2: 屬於營業 | D2: 屬於營業 | E2: 合計 | F2: 屬於營業 | G2: 屬於營業 | H2: 合計
B3: 費用別 | C3: 成本者 | D3: 費用者 | F3: 成本者 | G3: 費用者
B4: 用人費用
B5: 薪資費用 | C5: =TB!I236+TB!I239 -> 7889677 | D5: =TB!I304 -> 9433488 | E5: =C5+D5 -> 17323165 | F5: 5519670 | G5: 7841710 | H5: =F5+G5 -> 13361380
B6: 勞健保費用 | C6: 852122 | D6: 650353 | E6: =C6+D6 -> 1502475 | F6: 676797 | G6: 767358 | H6: =F6+G6 -> 1444155
B7: 退休金費用 | C7: =TB!I262 -> 159998 | D7: =TB!I354 -> 353089 | E7: =C7+D7 -> 513087 | F7: 158598 | G7: 424485 | H7: =F7+G7 -> 583083
B8: 其他用人費用 | C8: =TB!I237+TB!I240 -> 1375269 | D8: =TB!I305 -> 676758 | E8: =C8+D8 -> 2052027 | F8: 753528 | G8: 735886 | H8: =F8+G8 -> 1489414
B9: 折舊費用 | C9: =TB!I252 -> 2945943 | D9: =TB!I320 -> 902651 | E9: =C9+D9 -> 3848594 | F9: 6463917 | G9: 1512255 | H9: =F9+G9 -> 7976172
B10: 攤銷費用 | C10: =TB!I253 -> 15876 | D10: =TB!I321 -> 35231 | E10: =D10 -> 35231 | F10: – | G10: 101268 | H10: =G10 -> 101268
B12: 加班費
B13: 伙食費
B20: 直接人工 | C20: =[2]當期損益表!C28 -> 18984961 | D20: =C20/E5 -> 1.0959291
B21: 製-伙 食 費 | C21: =[2]當期損益表!C37 -> 1162140
B22: 製-加班費 | C22: =[2]當期損益表!C41 -> 4015188
B23: 製-保 險 費 | C23: =[2]當期損益表!C34 -> 2287870
B24: 製-退職金 | C24: =[2]當期損益表!C42 -> 882411
B26: 薪資支出 | C26: =[2]當期損益表!C54 -> 14795026 | D26: =C26/E5 -> 0.85406021
B27: 保 險 費 | C27: =[2]當期損益表!C63 -> 1232742 | D27: =C27*D26 -> 1052835.9
B28: 伙 食 費 | C28: =[2]當期損益表!C68 -> 667200
B29: 加班費 | C29: =[2]當期損益表!C74 -> 1469201
B30: 退職金 | C30: =[2]當期損益表!C76 -> 316312 | D30: =C30*D26 -> 270149.49
C32: 成本 | D32: 費用
B33: 保險費
B34: 退職金

Sheet 附註不動產
C1: 土 地 | F1: 房屋及建築 | I1: 機器設備 | L1: 運輸設備 | O1: 辦公設備 | R1: 其他設備 | U1: 合 計
A2: 成 本
A3: 112年1月1日 | C3: $ | D3: 0 | F3: $ | G3: 9848566 | I3: $ | J3: 41821547 | L3: $ | M3: 6888571 | O3: $ | P3: 689337 | R3: $ | S3: 1546871 | U3: $ | V3: =SUM(D3:S3) -> 60794892
A4: 增 添 | G4: 1149762 | J4: 1667144 | M4: 1465730 | P4: 21989 | S4: 596200 | V4: =SUM(D4:S4) -> 4900825
A5: 重分類 | G5: 7314286 | J5: -7314286 | M5: - | P5: - | S5: - | V5: -
A6: 112年12月31日 | D6: 0 | G6: =SUM(G3:G5) -> 18312614 | J6: =SUM(J3:J5) -> 36174405 | M6: =SUM(M3:M5) -> 8354301 | P6: =SUM(P3:P5) -> 711326 | S6: =SUM(S3:S5) -> 2143071 | V6: =SUM(V3:V5) -> 65695717
A7: 增 添 | G7: - | J7: 1170000 | M7: 1044720 | P7: 103634 | S7: 69900 | V7: =SUM(D7:S7) -> 2388254
A8: 處 分 | G8: - | J8: - | M8: - | P8: - | S8: - | V8: -
A9: 113年12月31日 | C9: $ | D9: 0 | F9: $ | G9: =SUM(G6:G8) -> 18312614 | I9: $ | J9: =SUM(J6:J8) -> 37344405 | L9: $ | M9: =SUM(M6:M8) -> 9399021 | O9: $ | P9: =SUM(P6:P8) -> 814960 | R9: $ | S9: =SUM(S6:S8) -> 2212971 | V9: =SUM(V6:V8) -> 68083971
A10: 累計折舊
A11: 112年1月1日 | C11: $ | F11: $ | G11: 542287 | I11: $ | J11: 927671 | L11: $ | M11: 221048 | O11: $ | P11: 81594 | R11: $ | S11: 45888 | U11: $ | V11: =SUM(F11:U11) -> 1818488
A12: 折 舊 | G12: 2105404 | J12: 4125964 | M12: 1163497 | P12: 176936 | S12: 404371 | V12: =SUM(D12:S12) -> 7976172
A13: 重分類 | G13: 110822 | J13: -110822 | M13: - | P13: - | S13: - | V13: -
A14: 112年12月31日 | G14: =SUM(G11:G13) -> 2758513 | J14: =SUM(J11:J13) -> 4942813 | M14: =SUM(M11:M13) -> 1384545 | P14: =SUM(P11:P13) -> 258530 | S14: =SUM(S11:S13) -> 450259 | V14: =SUM(V11:V13) -> 9794660
A15: 折 舊 | G15: 940896 | J15: 1916250 | M15: 645945 | P15: 122398 | S15: 223105 | V15: =SUM(D15:S15) -> 3848594
A16: 處 分 | G16: - | J16: - | M16: - | P16: - | S16: - | V16: -
A17: 113年12月31日 | C17: $ | F17: $ | G17: =SUM(G14:G16) -> 3699409 | I17: $ | J17: =SUM(J14:J16) -> 6859063 | L17: $ | M17: =SUM(M14:M16) -> 2030490 | O17: $ | P17: =SUM(P14:P16) -> 380928 | R17: $ | S17: =SUM(S14:S16) -> 673364 | U17: $ | V17: =SUM(V14:V16) -> 13643254
A19: 帳面價值
A20: 113年12月31日 | C20: $ | D20: =D9-D17 -> 0 | F20: $ | G20: =G9-G17 -> 14613205 | I20: $ | J20: =J9-J17 -> 30485342 | L20: $ | M20: =M9-M17 -> 7368531 | O20: $ | P20: =P9-P17 -> 434032 | R20: $ | S20: =S9-S17 -> 1539607 | U20: $ | V20: =V9-V17 -> 54440717
A21: 112年1月1日 | C21: $ | D21: =D3-D11 -> 0 | F21: $ | G21: =G3-G11 -> 9306279 | I21: $ | J21: =J3-J11 -> 40893876 | L21: $ | M21: =M3-M11 -> 6667523 | O21: $ | P21: =P3-P11 -> 607743 | R21: $ | S21: =S3-S11 -> 1500983 | U21: $ | V21: =V3-V11 -> 58976404
A22: 112年12月31日 | C22: $ | D22: =D6-D14 -> 0 | F22: $ | G22: =G6-G14 -> 15554101 | I22: $ | J22: =J6-J14 -> 31231592 | L22: $ | M22: =M6-M14 -> 6969756 | O22: $ | P22: =P6-P14 -> 452796 | R22: $ | S22: =S6-S14 -> 1692812 | U22: $ | V22: =V6-V14 -> 55901057

Sheet TB
A1: 會計項目 | B1: 科項名稱 | C1: 期初借方 | D1: 期初貸方 | E1: 本期借方 | F1: 本期貸方 | G1: 本期借餘 | H1: 本期貸餘 | I1: 期末借餘 | J1: 期末貸餘
A2: 1000 | B2: 資產總額 | C2: 0 | D2: 0 | E2: 0 | F2: 0 | G2: 0 | H2: 0 | I2: 0 | J2: 0
A3: 1100 | B3: 流動資產 | C3: 0 | D3: 0 | E3: 0 | F3: 0 | G3: 0 | H3: 0 | I3: 0 | J3: 0
A4: 1111 | B4: 現金 | C4: 36270 | D4: 0 | E4: 738871 | F4: 738931 | G4: 0 | H4: 60 | I4: 36210 | J4: 0
A5: 1112 | B5: 銀行存款 | C5: 0 | D5: 0 | E5: 15 | F5: 15 | G5: 0 | H5: 0 | I5: 0 | J5: 0
A6: 1112-1 | B6: 銀行存款-合作金庫 | C6: 4171035 | D6: 0 | E6: 45709621 | F6: 47826998 | G6: 0 | H6: 2117377 | I6: 2053658 | J6: 0
A7: 1112-2 | B7: 定期存單-合作金庫 | C7: 4459 | D7: 0 | E7: 303776 | F7: 300000 | G7: 3776 | H7: 0 | I7: 8235 | J7: 0
A8: 1112-3 | B8: 銀行存款-彰銀活存 | C8: 3376184 | D8: 0 | E8: 48273859 | F8: 51558215 | G8: 0 | H8: 3284356 | I8: 91828 | J8: 0
A9: 1112-4 | B9: 銀行存款-彰銀支存 | C9: 0 | D9: 0 | E9: 5017388 | F9: 4856010 | G9: 161378 | H9: 0 | I9: 161378 | J9: 0
A10: 1112-5 | B10: 銀行存款-彰銀活存設質 | C10: 631 | D10: 0 | E10: 0 | F10: 0 | G10: 0 | H10: 0 | I10: 631 | J10: 0
A11: 1112-6 | B11: 銀行存款-土銀活存 | C11: 0 | D11: 0 | E11: 12076597 | F11: 9019954 | G11: 3056643 | H11: 0 | I11: 3056643 | J11: 0
A12: 1113 | B12: 約當現金 | C12: 0 | D12: 0 | E12: 0 | F12: 0 | G12: 0 | H12: 0 | I12: 0 | J12: 0
A13: 1114 | B13: 短期投資 | C13: 0 | D13: 0 | E13: 0 | F13: 0 | G13: 0 | H13: 0 | I13: 0 | J13: 0
... A386: 9999 | B386: 所得稅費用 | C386: 0 | D386: 0 | E386: 46762 | F386: 0 | G386: 46762 | H386: 0 | I386: 46762 | J386: 0

Sheet BS
A1: 資產項目 | B1: 資產項目名稱 | C1: 資產金額小計 | D1: 資產金額合計 | E1: 負債及淨值項目 | F1: 負債及淨值項目名稱 | G1: 負債及淨值金額小計 | H1: 負債及淨值金額合計
A2: 1100 | B2: 流動資產 | C2: 0 | D2: 28124966 | E2: 2100 | F2: 流動負債 | G2: 0 | H2: 22673269
A3: 1111 | B3: 現金 | C3: 36210 | D3: 0 | E3: 2110 | F3: 短期借款 | G3: 6701448 | H3: 0
A4: 1112-1 | B4: 銀行存款-合作金庫 | C4: 2053658 | D4: 0 | E4: 2112-1 | F4: 一年內到期長期借款 | G4: 6701448 | H4: 0
A5: 1112-2 | B5: 定期存單-合作金庫 | C5: 8235 | D5: 0 | E5: 2120 | F5: 應付票據 | G5: 311654 | H5: 0
A6: 1112-3 | B6: 銀行存款-彰銀活存 | C6: 91828 | D6: 0 | E6: 2121 | F6: 應付帳款 | G6: 4339539 | H6: 0
A7: 1112-4 | B7: 銀行存款-彰銀支存 | C7: 161378 | D7: 0 | E7: 2130 | F7: 其他應付款 | G7: 11112008 | H7: 0
A8: 1112-5 | B8: 銀行存款-彰銀活存設質 | C8: 631 | D8: 0 | E8: 2131 | F8: 應付費用 | G8: 7868422 | H8: 0
A9: 1112-6 | B9: 銀行存款-土銀活存 | C9: 3056643 | D9: 0 | E9: 2131-2 | F9: 應付薪資 | G9: 3012320 | H9: 0
A10: 1121 | B10: 應收票據 | C10: 4597726 | D10: 0 | E10: 2131-3 | F10: 應付利息 | G10: 15186 | H10: 0
A11: 1123 | B11: 應收帳款 | C11: 13444980 | D11: 0 | E11: 2132 | F11: 應付稅捐 | G11: 216080 | H11: 0
A12: 1129-3 | B12: 其他應收款 | C12: 1028274 | D12: 0 | E12: 2136 | F12: 預收款項 | G12: 1202 | H12: 0
A13: 1130 | B13: 存貨 | C13: 2961265 | D13: 0 | E13: 2137 | F13: 預收貨款 | G13: 1202 | H13: 0
... A18: 1191 | B18: 暫付款 | C18: 285908 | D18: 0 | E18: 2000 | F18: 負債總額 | G18: 0 | H18: 44274434
A19: 1199-1 | B19: 應退稅額 | C19: 2903 | D19: 0 | G19: 0 | H19: 0
A20: 1200 | B20: 非流動資產 | C20: 0 | D20: 77422803 | E20: 3100 | F20: 資本或股本(實收) | G20: 0 | H20: 90000000
A21: 1400 | B21: 固定資產 | C21: 54440717 | D21: 0 | E21: 3110 | F21: 股本(登記) | G21: 90000000 | H21: 0
A22: 1431 | B22: 房屋及建築 | C22: 18312614 | D22: 0 | E22: 3300 | F22: 資本公積 | G22: 0 | H22: 1400000
A23: 1432 | B23: 累計折舊-房屋及建築 | C23: -3699409 | D23: 0 | E23: 3400 | F23: 保留盈餘 | G23: 0 | H23: -30126665
A24: 1441 | B24: 機器設備 | C24: 37344405 | D24: 0 | E24: 3430 | F24: 累積盈虧 | G24: -30313711 | H24: 0
A25: 1442 | B25: 累計折舊-機器設備 | C25: -6859063 | D25: 0 | E25: 3432 | F25: 累積盈虧(87年以後) | G25: -30313711 | H25: 0
A26: 1451 | B26: 運輸設備 | C26: 9399021 | D26: 0 | E26: 3440 | F26: 本期損益 | G26: 187046 | H26: 0
A27: 1452 | B27: 累計折舊-運輸設備 | C27: -2030490 | D27: 0 | E27: 3000 | F27: 權益總額 | G27: 0 | H27: 61273335
A28: 1461 | B28: 辦公設備 | C28: 814960 | D28: 0 | G28: 0 | H28: 0
A29: 1462 | B29: 累計折舊-辦公設備 | C29: -380928 | D29: 0 | G29: 0 | H29: 0
A30: 1491 | B30: 其他固定資產 | C30: 2212971 | D30: 0 | G30: 0 | H30: 0
A31: 1492 | B31: 累計折舊-其他固定資產 | C31: -673364 | D31: 0 | G31: 0 | H31: 0
A32: 1510 | B32: 無形資產 | C32: 479288 | D32: 0 | G32: 0 | H32: 0
A33: 1511 | B33: 無形資產-累計攤折 | C33: -234570 | D33: 0 | G33: 0 | H33: 0
A34: 1900 | B34: 其他非流動資產 | C34: 22737368 | D34: 0 | G34: 0 | H34: 0
A35: 1901 | B35: 存出保證金 | C35: 16825600 | D35: 0 | G35: 0 | H35: 0
A36: 1903 | B36: 預付設備款 | C36: 1596848 | D36: 0 | G36: 0 | H36: 0
A37: 1904-1 | B37: 遞延所得稅資產 | C37: 4314920 | D37: 0 | G37: 0 | H37: 0
C38: 0 | D38: 0 | G38: 0 | H38: 0
A39: 1000 | B39: 資產總額 | C39: 0 | D39: 105547769 | E39: 9000 | F39: 負債及權益總額 | G39: 0 | H39: 105547769

Sheet IS
A1: 項目代號 | B1: 項目名稱 | C1: 小計金額 | D1: 合計金額 | E1: 百分比
A2: 4000 | B2: 營業收入淨額 | C2: 0 | D2: 52599315 | E2: 100
A3: 4100 | B3: 營業收入總額 | C3: 53353003 | D3: 0 | E3: 101.43
A4: 4101 | B4: 營業收入 | C4: 53353003 | D4: 0 | E4: 101.43
A5: 4202 | B5: 銷貨折讓 | C5: -753688 | D5: 0 | E5: -1.43
B6: 營業收入淨額 | C6: 0 | D6: 52599315 | E6: 100
A7: 5900 | B7: 營業成本 | C7: 0 | D7: 33039914 | E7: 62.81
A8: 5000 | B8: 進銷成本 | C8: 0 | D8: 0 | E8: 0
A9: 5100 | B9: 直接原料 | C9: 9063511 | D9: 0 | E9: 17.23
A10: 5110 | B10: 期初存料-原料 | C10: 2450275 | D10: 0 | E10: 4.65
A11: 5120 | B11: 本期進料-原料(淨額) | C11: 9574501 | D11: 0 | E11: 18.2
A12: 5121 | B12: 原料進料 | C12: 9574501 | D12: 0 | E12: 18.2
A13: 5130 | B13: 期末存貨-原料 | C13: -2961265 | D13: 0 | E13: -5.63
A14: 5300 | B14: 直接人工 | C14: 7014248 | D14: 0 | E14: 13.33
A15: 5301 | B15: 直接人工-免稅加班費 | C15: 1242398 | D15: 0 | E15: 2.36
A16: 5400 | B16: 製造費用**** | C16: 15719757 | D16: 0 | E16: 29.88
A17: 5401 | B17: 製-間接人工 | C17: 875429 | D17: 0 | E17: 1.66
A18: 5401-1 | B18: 製-間接人工(免稅加班費) | C18: 132871 | D18: 0 | E18: 0.25
... A41: 5570 | B41: 產銷成本 | C41: 33039914 | D41: 0 | E41: 62.81
B42: 營業毛利 | C42: 0 | D42: 19559401 | E42: 37.18
A43: 6000 | B43: 營業費用及損失總額 | C43: 0 | D43: 19136173 | E43: 36.38
A44: 6010 | B44: 薪資支出 | C44: 9433488 | D44: 0 | E44: 17.93
A45: 6010-1 | B45: 薪資支出(免稅加班費) | C45: 676758 | D45: 0 | E45: 1.28
A46: 6011 | B46: 租金支出 | C46: 1311571 | D46: 0 | E46: 2.49
A47: 6012 | B47: 文具用品 | C47: 69020 | D47: 0 | E47: 0.13
A48: 6013 | B48: 旅費 | C48: 37989 | D48: 0 | E48: 0.07
A49: 6014 | B49: 運費 | C49: 1527347 | D49: 0 | E49: 2.9
A50: 6015 | B50: 郵電費 | C50: 217644 | D50: 0 | E50: 0.41
A51: 6016 | B51: 修繕費 | C51: 568710 | D51: 0 | E51: 1.08
A52: 6017 | B52: 廣告費 | C52: 64257 | D52: 0 | E52: 0.12
A53: 6019 | B53: 保險費 | C53: 1105338 | D53: 0 | E53: 2.1
A54: 6020 | B54: 交際費 | C54: 25057 | D54: 0 | E54: 0.04
... A64: 603217 | B64: 參展費 | C64: 175184 | D64: 0 | E64: 0.33
B65: 營業淨利 | C65: 0 | D65: 423228 | E65: 0.8
A66: 7000 | B66: 非營業收入總額 | C66: 0 | D66: 514722 | E66: 0.97
A67: 7038 | B67: 利息收入 | C67: 160806 | D67: 0 | E67: 0.3
A68: 7044 | B68: 其他收入 | C68: 328916 | D68: 0 | E68: 0.62
A69: 7044-1 | B69: 出售下腳及廢料收入 | C69: 25000 | D69: 0 | E69: 0.04
A70: 8000 | B70: 非營業損失及費用總額 | C70: 0 | D70: 704142 | E70: 1.33
A71: 8046 | B71: 利息支出 | C71: 704142 | D71: 0 | E71: 1.33
B72: 稅前淨利 | C72: 0 | D72: 233808 | E72: 0.44
A73: 9999 | B73: 所得稅費用 | C73: 46762 | D73: 0 | E73: 0.08
B74: 稅後淨利 | C74: 0 | D74: 187046 | E74: 0

Sheet VI-2資產
B1: 牛津會計師事務所
B2: 公司
B3: 商 業 會 計 項 目 表—資產
E4: (財簽適用)
B5: 三級 項目 | C5: 四級 項目 | D5: 會計項目名稱 | E5: 資產金額
E6: 105年 | F6: 104年 | G6: 103年 | H6: 增加(減少)數
H7: 105年度 | I7: 104年度
E8: (1) | F8: (2) | G8: (3) | H8: (2)-(1) | I8: (3)-(2) | J8: 篩選數字
D9: 資 產 | J9: =SUM(E9:I9) -> 0
D10: 流動資產 | J10: =SUM(E10:I10) -> 0
A11: 111現金及約當現金 | C11: 1111 | D11: 庫存現金 | E11: 1 | F11: 2 | G11: 3 | H11: =F11-E11 -> 1 | I11: =G11-F11 -> 1 | J11: =SUM(E11:I11) -> 8
A12: 111現金及約當現金 | C12: 1112 | D12: 零用金/週轉金 | E12: 1 | F12: 2 | G12: 3 | H12: =F12-E12 -> 1 | I12: =G12-F12 -> 1 | J12: =SUM(E12:I12) -> 8
A13: 111現金及約當現金 | C13: 1113 | D13: 銀行存款 | E13: 1 | F13: 2 | G13: 3 | H13: =F13-E13 -> 1 | I13: =G13-F13 -> 1 | J13: =SUM(E13:I13) -> 8
A14: 111現金及約當現金 | C14: 1114 | D14: 在途現金 | E14: 1 | F14: 2 | G14: 3 | H14: =F14-E14 -> 1 | I14: =G14-F14 -> 1 | J14: =SUM(E14:I14) -> 8
A15: 111現金及約當現金 | C15: 1115 | D15: 約當現金 | E15: 1 | F15: 2 | G15: 3 | H15: =F15-E15 -> 1 | I15: =G15-F15 -> 1 | J15: =SUM(E15:I15) -> 8
A16: 111現金及約當現金 | B16: 111 | D16: 現金及約當現金 | E16: =SUBTOTAL(9,E11:E15) -> 5 | F16: =SUBTOTAL(9,F11:F15) -> 10 | G16: =SUBTOTAL(9,G11:G15) -> 15 | H16: =SUBTOTAL(9,H11:H15) -> 5 | I16: =SUBTOTAL(9,I11:I15) -> 5 | J16: =SUM(E16:I16) -> 40
A17: 112透過損益按公允價值衡量之金融資產－流動 | C17: 1121 | D17: 透過損益按公允價值衡量之金融資產－流動 | H17: =F17-E17 -> 0 | I17: =G17-F17 -> 0 | J17: =SUM(E17:I17) -> 0
A18: 112透過損益按公允價值衡量之金融資產－流動 | C18: 1122 | D18: 透過損益按公允價值衡量之金融資產評價調整—流動 | H18: =F18-E18 -> 0 | I18: =G18-F18 -> 0 | J18: =SUM(E18:I18) -> 0
A19: 112透過損益按公允價值衡量之金融資產－流動 | B19: 112 | D19: 透過損益按公允價值衡量之金融資產－流動 | E19: =SUBTOTAL(9,E17:E18) -> 0 | F19: =SUBTOTAL(9,F17:F18) -> 0 | G19: =SUBTOTAL(9,G17:G18) -> 0 | H19: =SUBTOTAL(9,H17:H18) -> 0 | I19: =SUBTOTAL(9,I17:I18) -> 0 | J19: =SUM(E19:I19) -> 0
A20: 113備供出售金融資產－流動 | C20: 1131 | D20: 備供出售金融資產－流動 | H20: =F20-E20 -> 0 | I20: =G20-F20 -> 0 | J20: =SUM(E20:I20) -> 0
A21: 113備供出售金融資產－流動 | C21: 1132 | D21: 備供出售金融資產評價調整—流動 | H21: =F21-E21 -> 0 | I21: =G21-F21 -> 0 | J21: =SUM(E21:I21) -> 0
A22: 113備供出售金融資產－流動 | C22: 1133 | D22: 累計減損—備供出售金融資產—流動 | H22: =F22-E22 -> 0 | I22: =G22-F22 -> 0 | J22: =SUM(E22:I22) -> 0
A23: 113備供出售金融資產－流動 | B23: 113 | D23: 備供出售金融資產－流動 | E23: =SUBTOTAL(9,E20:E22) -> 0 | F23: =SUBTOTAL(9,F20:F22) -> 0 | G23: =SUBTOTAL(9,G20:G22) -> 0 | H23: =SUBTOTAL(9,H20:H22) -> 0 | I23: =SUBTOTAL(9,I20:I22) -> 0 | J23: =SUM(E23:I23) -> 0
A24: 114以成本衡量之金融資產－流動 | C24: 1141 | D24: 以成本衡量之金融資產－流動 | H24: =F24-E24 -> 0 | I24: =G24-F24 -> 0 | J24: =SUM(E24:I24) -> 0
A25: 114以成本衡量之金融資產－流動 | C25: 1142 | D25: 累計減損—以成本衡量之金融資產—流動 | H25: =F25-E25 -> 0 | I25: =G25-F25 -> 0 | J25: =SUM(E25:I25) -> 0
A26: 114以成本衡量之金融資產－流動 | B26: 114 | D26: 以成本衡量之金融資產－流動 | E26: =SUBTOTAL(9,E24:E25) -> 0 | F26: =SUBTOTAL(9,F24:F25) -> 0 | G26: =SUBTOTAL(9,G24:G25) -> 0 | H26: =SUBTOTAL(9,H24:H25) -> 0 | I26: =SUBTOTAL(9,I24:I25) -> 0 | J26: =SUM(E26:I26) -> 0
A27: 115無活絡市場之債務工具投資－流動 | C27: 1151 | D27: 無活絡市場之債務工具投資－流動 | H27: =F27-E27 -> 0 | I27: =G27-F27 -> 0 | J27: =SUM(E27:I27) -> 0
A28: 115無活絡市場之債務工具投資－流動 | C28: 1152 | D28: 累計減損—無活絡市場之債務工具投資—流動 | H28: =F28-E28 -> 0 | I28: =G28-F28 -> 0 | J28: =SUM(E28:I28) -> 0
A29: 115無活絡市場之債務工具投資－流動 | B29: 115 | D29: 無活絡市場之債務工具投資－流動 | E29: =SUBTOTAL(9,E27:E28) -> 0 | F29: =SUBTOTAL(9,F27:F28) -> 0 | G29: =SUBTOTAL(9,G27:G28) -> 0 | H29: =SUBTOTAL(9,H27:H28) -> 0 | I29: =SUBTOTAL(9,I27:I28) -> 0 | J29: =SUM(E29:I29) -> 0
A30: 116持有至到期日金融資產—流動 | C30: 1161 | D30: 持有至到期日金融資產—流動 | H30: =F30-E30 -> 0 | I30: =G30-F30 -> 0 | J30: =SUM(E30:I30) -> 0
A31: 116持有至到期日金融資產—流動 | C31: 1162 | D31: 累計減損—持有至到期日金融資產—流動 | H31: =F31-E31 -> 0 | I31: =G31-F31 -> 0 | J31: =SUM(E31:I31) -> 0
A32: 116持有至到期日金融資產—流動 | B32: 116 | D32: 持有至到期日金融資產—流動 | E32: =SUBTOTAL(9,E30:E31) -> 0 | F32: =SUBTOTAL(9,F30:F31) -> 0 | G32: =SUBTOTAL(9,G30:G31) -> 0 | H32: =SUBTOTAL(9,H30:H31) -> 0 | I32: =SUBTOTAL(9,I30:I31) -> 0 | J32: =SUM(E32:I32) -> 0
A33: 117避險之衍生金融資產－流動 | C33: 1171 | D33: 避險之衍生金融資產－流動 | H33: =F33-E33 -> 0 | I33: =G33-F33 -> 0 | J33: =SUM(E33:I33) -> 0
A34: 117避險之衍生金融資產－流動 | C34: 1172 | D34: 避險之衍生金融資產評價調整—流動 | H34: =F34-E34 -> 0 | I34: =G34-F34 -> 0 | J34: =SUM(E34:I34) -> 0
A35: 117避險之衍生金融資產－流動 | B35: 117 | D35: 避險之衍生金融資產－流動 | E35: =SUBTOTAL(9,E33:E34) -> 0 | F35: =SUBTOTAL(9,F33:F34) -> 0 | G35: =SUBTOTAL(9,G33:G34) -> 0 | H35: =SUBTOTAL(9,H33:H34) -> 0 | I35: =SUBTOTAL(9,I33:I34) -> 0 | J35: =SUM(E35:I35) -> 0
A36: 118應收票據淨額 | C36: 1181 | D36: 應收票據 | H36: =F36-E36 -> 0 | I36: =G36-F36 -> 0 | J36: =SUM(E36:I36) -> 0
A37: 118應收票據淨額 | C37: 1182 | D37: 應收票據貼現 | H37: =F37-E37 -> 0 | I37: =G37-F37 -> 0 | J37: =SUM(E37:I37) -> 0
A38: 118應收票據淨額 | C38: 1183 | D38: 應收票據—關係人 | H38: =F38-E38 -> 0 | I38: =G38-F38 -> 0 | J38: =SUM(E38:I38) -> 0
A39: 118應收票據淨額 | C39: 1184 | D39: 其他應收票據 | H39: =F39-E39 -> 0 | I39: =G39-F39 -> 0 | J39: =SUM(E39:I39) -> 0
A40: 118應收票據淨額 | C40: 1185 | D40: 備抵呆帳—應收票據 | H40: =F40-E40 -> 0 | I40: =G40-F40 -> 0 | J40: =SUM(E40:I40) -> 0
A41: 118應收票據淨額 | B41: 118 | D41: 應收票據淨額 | E41: =SUBTOTAL(9,E36:E40) -> 0 | F41: =SUBTOTAL(9,F36:F40) -> 0 | G41: =SUBTOTAL(9,G36:G40) -> 0 | H41: =SUBTOTAL(9,H36:H40) -> 0 | I41: =SUBTOTAL(9,I36:I40) -> 0 | J41: =SUM(E41:I41) -> 0
A42: 119應收帳款淨額 | C42: 1191 | D42: 應收帳款 | H42: =F42-E42 -> 0 | I42: =G42-F42 -> 0 | J42: =SUM(E42:I42) -> 0
A43: 119應收帳款淨額 | C43: 1192 | D43: 備抵銷售退回及折讓 | H43: =F43-E43 -> 0 | I43: =G43-F43 -> 0 | J43: =SUM(E43:I43) -> 0
A44: 119應收帳款淨額 | C44: 1193 | D44: 應收分期帳款 | H44: =F44-E44 -> 0 | I44: =G44-F44 -> 0 | J44: =SUM(E44:I44) -> 0
A45: 119應收帳款淨額 | C45: 1194 | D45: 未實現利息收入 | H45: =F45-E45 -> 0 | I45: =G45-F45 -> 0 | J45: =SUM(E45:I45) -> 0
A46: 119應收帳款淨額 | C46: 1195 | D46: 應收租賃款 | H46: =F46-E46 -> 0 | I46: =G46-F46 -> 0 | J46: =SUM(E46:I46) -> 0
A47: 119應收帳款淨額 | C47: 1196 | D47: 未賺得融資收益 | H47: =F47-E47 -> 0 | I47: =G47-F47 -> 0 | J47: =SUM(E47:I47) -> 0
A48: 119應收帳款淨額 | C48: 1197 | D48: 應收帳款—關係人 | H48: =F48-E48 -> 0 | I48: =G48-F48 -> 0 | J48: =SUM(E48:I48) -> 0
A49: 119應收帳款淨額 | C49: 1198 | D49: 備抵呆帳—應收帳款 | H49: =F49-E49 -> 0 | I49: =G49-F49 -> 0 | J49: =SUM(E49:I49) -> 0
A50: 119應收帳款淨額 | B50: 119 | D50: 應收帳款淨額 | E50: =SUBTOTAL(9,E42:E49) -> 0 | F50: =SUBTOTAL(9,F42:F49) -> 0 | G50: =SUBTOTAL(9,G42:G49) -> 0 | H50: =SUBTOTAL(9,H42:H49) -> 0 | I50: =SUBTOTAL(9,I42:I49) -> 0 | J50: =SUM(E50:I50) -> 0
A51: 120應收建造合約款 | C51: 120 | D51: 應收建造合約款 | H51: =F51-E51 -> 0 | I51: =G51-F51 -> 0 | J51: =SUM(E51:I51) -> 0
A52: 120應收建造合約款 | B52: 120 | D52: 應收建造合約款 | E52: =SUM(E51) -> 0 | F52: =SUM(F51) -> 0 | G52: =SUM(G51) -> 0 | H52: =SUM(H51) -> 0 | I52: =SUM(I51) -> 0 | J52: =SUM(E52:I52) -> 0
A53: 121其他應收款 | C53: 1211 | D53: 應收收益 | E53: 0 | F53: 0 | H53: =F53-E53 -> 0 | I53: =G53-F53 -> 0 | J53: =SUM(E53:I53) -> 0
A54: 121其他應收款 | C54: 1212 | D54: 其他應收款—關係人 | H54: =F54-E54 -> 0 | I54: =G54-F54 -> 0 | J54: =SUM(E54:I54) -> 0
A55: 121其他應收款 | C55: 1213 | D55: 其他應收款—其他 | H55: =F55-E55 -> 0 | I55: =G55-F55 -> 0 | J55: =SUM(E55:I55) -> 0
A56: 121其他應收款 | C56: 1214 | D56: 備抵呆帳—其他應收款 | H56: =F56-E56 -> 0 | I56: =G56-F56 -> 0 | J56: =SUM(E56:I56) -> 0
A57: 121其他應收款 | B57: 121 | D57: 其他應收款 | E57: =SUBTOTAL(9,E53:E56) -> 0 | F57: =SUBTOTAL(9,F53:F56) -> 0 | G57: =SUBTOTAL(9,G53:G56) -> 0 | H57: =SUBTOTAL(9,H53:H56) -> 0 | I57: =SUBTOTAL(9,I53:I56) -> 0 | J57: =SUM(E57:I57) -> 0
A58: 122本期所得稅資產 | C58: 1221 | D58: 應收所得稅退稅款 | H58: =F58-E58 -> 0 | I58: =G58-F58 -> 0 | J58: =SUM(E58:I58) -> 0
A59: 122本期所得稅資產 | C59: 1222 | D59: 預付所得稅 | H59: =F59-E59 -> 0 | I59: =G59-F59 -> 0 | J59: =SUM(E59:I59) -> 0
A60: 122本期所得稅資產 | B60: 122 | D60: 本期所得稅資產 | E60: =SUBTOTAL(9,E58:E59) -> 0 | F60: =SUBTOTAL(9,F58:F59) -> 0 | G60: =SUBTOTAL(9,G58:G59) -> 0 | H60: =SUBTOTAL(9,H58:H59) -> 0 | I60: =SUBTOTAL(9,I58:I59) -> 0 | J60: =SUM(E60:I60) -> 0
A61: 123-124存貨 | C61: 1231 | D61: 商品存貨 | H61: =F61-E61 -> 0 | I61: =G61-F61 -> 0 | J61: =SUM(E61:I61) -> 0
A62: 123-124存貨 | C62: 1232 | D62: 寄銷品 | H62: =F62-E62 -> 0 | I62: =G62-F62 -> 0 | J62: =SUM(E62:I62) -> 0
A63: 123-124存貨 | C63: 1233 | D63: 在途商品 | H63: =F63-E63 -> 0 | I63: =G63-F63 -> 0 | J63: =SUM(E63:I63) -> 0
A64: 123-124存貨 | C64: 1234 | D64: 備抵存貨跌價損失(買賣業) | H64: =F64-E64 -> 0 | I64: =G64-F64 -> 0 | J64: =SUM(E64:I64) -> 0
A65: 123-124存貨 | C65: 1235 | D65: 製成品 | H65: =F65-E65 -> 0 | I65: =G65-F65 -> 0 | J65: =SUM(E65:I65) -> 0
A66: 123-124存貨 | C66: 1236 | D66: 副產品 | H66: =F66-E66 -> 0 | I66: =G66-F66 -> 0 | J66: =SUM(E66:I66) -> 0
A67: 123-124存貨 | C67: 1237 | D67: 在製品 | H67: =F67-E67 -> 0 | I67: =G67-F67 -> 0 | J67: =SUM(E67:I67) -> 0
A68: 123-124存貨 | C68: 1238 | D68: 委外加工 | H68: =F68-E68 -> 0 | I68: =G68-F68 -> 0 | J68: =SUM(E68:I68) -> 0
A69: 123-124存貨 | C69: 1239 | D69: 原料 | H69: =F69-E69 -> 0 | I69: =G69-F69 -> 0 | J69: =SUM(E69:I69) -> 0
A70: 123-124存貨 | C70: 1240 | D70: 物料 | H70: =F70-E70 -> 0 | I70: =G70-F70 -> 0 | J70: =SUM(E70:I70) -> 0
A71: 123-124存貨 | C71: 1241 | D71: 在途原物料 | H71: =F71-E71 -> 0 | I71: =G71-F71 -> 0 | J71: =SUM(E71:I71) -> 0
A72: 123-124存貨 | C72: 1242 | D72: 備抵存貨跌價損失(製造業) | H72: =F72-E72 -> 0 | I72: =G72-F72 -> 0 | J72: =SUM(E72:I72) -> 0
... A74: 123-124存貨 | C74: 1244 | D74: 在建工程 | H74: =F74-E74 -> 0 | I74: =G74-F74 -> 0 | J74: =SUM(E74:I74) -> 0
A75: 123-124存貨 | B75: 123-124 | D75: 存 貨 | E75: =SUBTOTAL(9,E61:E74) -> 0 | F75: =SUBTOTAL(9,F61:F74) -> 0 | G75: =SUBTOTAL(9,G61:G74) -> 0 | H75: =SUBTOTAL(9,H61:H74) -> 0 | I75: =SUBTOTAL(9,I61:I74) -> 0 | J75: =SUM(E75:I75) -> 0
A76: 126-127預付款項 | C76: 1261 | D76: 預付薪資 | H76: =F76-E76 -> 0 | I76: =G76-F76 -> 0 | J76: =SUM(E76:I76) -> 0
A77: 126-127預付款項 | C77: 1262 | D77: 預付租金 | H77: =F77-E77 -> 0 | I77: =G77-F77 -> 0 | J77: =SUM(E77:I77) -> 0
A78: 126-127預付款項 | C78: 1263 | D78: 預付保險費 | H78: =F78-E78 -> 0 | I78: =G78-F78 -> 0 | J78: =SUM(E78:I78) -> 0
A79: 126-127預付款項 | C79: 1264 | D79: 用品盤存 | H79: =F79-E79 -> 0 | I79: =G79-F79 -> 0 | J79: =SUM(E79:I79) -> 0
A80: 126-127預付款項 | C80: 1265 | D80: 其他預付費用 | H80: =F80-E80 -> 0 | I80: =G80-F80 -> 0 | J80: =SUM(E80:I80) -> 0
A81: 126-127預付款項 | C81: 1266 | D81: 預付貨款 | H81: =F81-E81 -> 0 | I81: =G81-F81 -> 0 | J81: =SUM(E81:I81) -> 0
A82: 126-127預付款項 | C82: 1267 | D82: 預付投資款 | H82: =F82-E82 -> 0 | I82: =G82-F82 -> 0 | J82: =SUM(E82:I82) -> 0
A83: 126-127預付款項 | C83: 1268 | D83: 進項稅額 | H83: =F83-E83 -> 0 | I83: =G83-F83 -> 0 | J83: =SUM(E83:I83) -> 0
A84: 126-127預付款項 | C84: 1269 | D84: 留抵稅額 | H84: =F84-E84 -> 0 | I84: =G84-F84 -> 0 | J84: =SUM(E84:I84) -> 0
A85: 126-127預付款項 | C85: 1270 | D85: 其他預付款項 | H85: =F85-E85 -> 0 | I85: =G85-F85 -> 0 | J85: =SUM(E85:I85) -> 0
A86: 126-127預付款項 | B86: 126-127 | D86: 預付款項 | E86: =SUBTOTAL(9,E76:E85) -> 0 | F86: =SUBTOTAL(9,F76:F85) -> 0 | G86: =SUBTOTAL(9,G76:G85) -> 0 | H86: =SUBTOTAL(9,H76:H85) -> 0 | I86: =SUBTOTAL(9,I76:I85) -> 0 | J86: =SUM(E86:I86) -> 0
A87: 128其他流動資產 | C87: 1281 | D87: 暫付款 | H87: =F87-E87 -> 0 | I87: =G87-F87 -> 0 | J87: =SUM(E87:I87) -> 0
A88: 128其他流動資產 | C88: 1282 | D88: 代付款 | H88: =F88-E88 -> 0 | I88: =G88-F88 -> 0 | J88: =SUM(E88:I88) -> 0
A89: 128其他流動資產 | C89: 1283 | D89: 員工借支 | H89: =F89-E89 -> 0 | I89: =G89-F89 -> 0 | J89: =SUM(E89:I89) -> 0
A90: 128其他流動資產 | C90: 1284 | D90: 存出保證金 | H90: =F90-E90 -> 0 | I90: =G90-F90 -> 0 | J90: =SUM(E90:I90) -> 0
A91: 128其他流動資產 | B91: 128 | D91: 其他流動資產 | E91: =SUBTOTAL(9,E87:E90) -> 0 | F91: =SUBTOTAL(9,F87:F90) -> 0 | G91: =SUBTOTAL(9,G87:G90) -> 0 | H91: =SUBTOTAL(9,H87:H90) -> 0 | I91: =SUBTOTAL(9,I87:I90) -> 0 | J91: =SUM(E91:I91) -> 0
D92: 非流動資產 | J92: =SUM(E92:I92) -> 0
A93: 131透過損益按公允價值衡量之金融資產—非流動 | C93: 1311 | D93: 透過損益按公允價值衡量之金融資產—非流動 | H93: =F93-E93 -> 0 | I93: =G93-F93 -> 0 | J93: =SUM(E93:I93) -> 0
A94: 131透過損益按公允價值衡量之金融資產—非流動 | C94: 1312 | D94: 透過損益按公允價值衡量之金融資評價調整—非流動 | H94: =F94-E94 -> 0 | I94: =G94-F94 -> 0 | J94: =SUM(E94:I94) -> 0
A95: 131透過損益按公允價值衡量之金融資產—非流動 | B95: 131 | D95: 透過損益按公允價值衡量之金融資產—非流動 | E95: =SUBTOTAL(9,E93:E94) -> 0 | F95: =SUBTOTAL(9,F93:F94) -> 0 | G95: =SUBTOTAL(9,G93:G94) -> 0 | H95: =SUBTOTAL(9,H93:H94) -> 0 | I95: =SUBTOTAL(9,I93:I94) -> 0 | J95: =SUM(E95:I95) -> 0
A96: 132備供出售金融資產—非流動 | C96: 1321 | D96: 備供出售金融資產—非流動 | H96: =F96-E96 -> 0 | I96: =G96-F96 -> 0 | J96: =SUM(E96:I96) -> 0
A97: 132備供出售金融資產—非流動 | C97: 1322 | D97: 備供出售金融資產評價調整—非流動 | H97: =F97-E97 -> 0 | I97: =G97-F97 -> 0 | J97: =SUM(E97:I97) -> 0
A98: 132備供出售金融資產—非流動 | C98: 1323 | D98: 累計減損—備供出售金融資產—非流動 | H98: =F98-E98 -> 0 | I98: =G98-F98 -> 0 | J98: =SUM(E98:I98) -> 0
A99: 132備供出售金融資產—非流動 | B99: 132 | D99: 備供出售金融資產—非流動 | E99: =SUBTOTAL(9,E96:E98) -> 0 | F99: =SUBTOTAL(9,F96:F98) -> 0 | G99: =SUBTOTAL(9,G96:G98) -> 0 | H99: =SUBTOTAL(9,H96:H98) -> 0 | I99: =SUBTOTAL(9,I96:I98) -> 0 | J99: =SUM(E99:I99) -> 0
A100: 133以成本衡量之金融資產—非流動 | C100: 1331 | D100: 以成本衡量之金融資產—非流動 | H100: =F100-E100 -> 0 | I100: =G100-F100 -> 0 | J100: =SUM(E100:I100) -> 0
A101: 133以成本衡量之金融資產—非流動 | C101: 1332 | D101: 累計減損—以成本衡量之金融資產—非流動 | H101: =F101-E101 -> 0 | I101: =G101-F101 -> 0 | J101: =SUM(E101:I101) -> 0
...

Sheet VI-2負債及權益
C1: 牛津會計師事務所
C2: 公司
C3: 商 業 會 計 項 目 表—負債及權益
C4: (財簽適用)
A5: 三級 項目 | B5: 三級 項目 | C5: 四級 項目 | D5: 會計項目名稱 | E5: 負債及權益金額
A6: 三級 項目 | E6: 105年 | F6: 104年 | G6: 103年 | H6: 增加(減少)數
H7: 105年度 | I7: 104年度
A8: 三級 項目 | E8: (1) | F8: (2) | G8: (3) | H8: (1)-(2) | I8: (2)-(3) | J8: 篩選數字
D9: 負債
D10: 流動負債
A11: 211短期借款 | C11: 2111 | D11: 銀行透支 | E11: 1 | F11: 2 | G11: 3 | H11: =E11-F11 -> -1 | I11: =F11-G11 -> -1 | J11: =SUM(E11:I11) -> 4
A12: 211短期借款 | C12: 2112 | D12: 銀行借款 | E12: 1 | F12: 2 | G12: 3 | H12: =E12-F12 -> -1 | I12: =F12-G12 -> -1 | J12: =SUM(E12:I12) -> 4
A13: 211短期借款 | C13: 2113 | D13: 短期借款—業主 | E13: 1 | F13: 2 | G13: 3 | H13: =E13-F13 -> -1 | I13: =F13-G13 -> -1 | J13: =SUM(E13:I13) -> 4
A14: 211短期借款 | C14: 2114 | D14: 短期借款—員工 | E14: 1 | F14: 2 | G14: 3 | H14: =E14-F14 -> -1 | I14: =F14-G14 -> -1 | J14: =SUM(E14:I14) -> 4
A15: 211短期借款 | C15: 2115 | D15: 短期借款—關係人 | E15: 1 | F15: 2 | G15: 3 | H15: =E15-F15 -> -1 | I15: =F15-G15 -> -1 | J15: =SUM(E15:I15) -> 4
A16: 211短期借款 | C16: 2116 | D16: 短期借款—其他 | E16: 1 | F16: 2 | G16: 3 | H16: =E16-F16 -> -1 | I16: =F16-G16 -> -1 | J16: =SUM(E16:I16) -> 4
A17: 211短期借款 | B17: 211 | D17: 短期借款 | E17: =SUBTOTAL(9,E11:E16) -> 6 | F17: =SUBTOTAL(9,F11:F16) -> 12 | G17: =SUBTOTAL(9,G11:G16) -> 18 | H17: =SUBTOTAL(9,H11:H16) -> -6 | I17: =SUBTOTAL(9,I11:I16) -> -6 | J17: =SUM(E17:I17) -> 24
A18: 212應付短期票券 | C18: 2121 | D18: 應付商業本票 | E18: 0 | F18: 0 | G18: 0 | H18: =E18-F18 -> 0 | I18: =F18-G18 -> 0 | J18: =SUM(E18:I18) -> 0
A19: 212應付短期票券 | C19: 2122 | D19: 銀行承兌匯票 | E19: 22 | F19: 0 | G19: 0 | H19: =E19-F19 -> 22 | I19: =F19-G19 -> 0 | J19: =SUM(E19:I19) -> 44
A20: 212應付短期票券 | C20: 2123 | D20: 其他應付短期票券 | E20: 0 | F20: 0 | G20: 0 | H20: =E20-F20 -> 0 | I20: =F20-G20 -> 0 | J20: =SUM(E20:I20) -> 0
A21: 212應付短期票券 | C21: 2124 | D21: 應付短期票券折價 | E21: 0 | F21: 0 | G21: 0 | H21: =E21-F21 -> 0 | I21: =F21-G21 -> 0 | J21: =SUM(E21:I21) -> 0
A22: 212應付短期票券 | B22: 212 | D22: 應付短期票券 | E22: =SUBTOTAL(9,E18:E21) -> 22 | F22: =SUBTOTAL(9,F18:F21) -> 0 | G22: =SUBTOTAL(9,G18:G21) -> 0 | H22: =SUBTOTAL(9,H18:H21) -> 22 | I22: =SUBTOTAL(9,I18:I21) -> 0 | J22: =SUM(E22:I22) -> 44
A23: 213透過損益按公允價值衡量之金融負債－流動 | C23: 2131 | D23: 透過損益按公允價值衡量之金融負債－流動 | E23: 0 | F23: 0 | G23: 0 | H23: =E23-F23 -> 0 | I23: =F23-G23 -> 0 | J23: =SUM(E23:I23) -> 0
A24: 213透過損益按公允價值衡量之金融負債－流動 | C24: 2132 | D24: 透過損益按公允價值衡量之金融負債評價調整—流動 | E24: 3333 | F24: 0 | G24: 0 | H24: =E24-F24 -> 3333 | I24: =F24-G24 -> 0 | J24: =SUM(E24:I24) -> 6666
A25: 213透過損益按公允價值衡量之金融負債－流動 | B25: 213 | D25: 透過損益按公允價值衡量之金融負債－流動 | E25: =SUBTOTAL(9,E23:E24) -> 3333 | F25: =SUBTOTAL(9,F23:F24) -> 0 | G25: =SUBTOTAL(9,G23:G24) -> 0 | H25: =SUBTOTAL(9,H23:H24) -> 3333 | I25: =SUBTOTAL(9,I23:I24) -> 0 | J25: =SUM(E25:I25) -> 6666
A26: 214避險之衍生金融負債—流動 | C26: 2141 | D26: 避險之衍生金融負債—流動 | E26: 0 | F26: 0 | G26: 0 | H26: =E26-F26 -> 0 | I26: =F26-G26 -> 0 | J26: =SUM(E26:I26) -> 0
A27: 214避險之衍生金融負債—流動 | C27: 2142 | D27: 避險之衍生金融負債評價調整—流動 | E27: 0 | F27: 0 | G27: 0 | H27: =E27-F27 -> 0 | I27: =F27-G27 -> 0 | J27: =SUM(E27:I27) -> 0
A28: 214避險之衍生金融負債—流動 | B28: 214 | D28: 避險之衍生金融負債—流動 | E28: =SUBTOTAL(9,E26:E27) -> 0 | F28: =SUBTOTAL(9,F26:F27) -> 0 | G28: =SUBTOTAL(9,G26:G27) -> 0 | H28: =SUBTOTAL(9,H26:H27) -> 0 | I28: =SUBTOTAL(9,I26:I27) -> 0 | J28: =SUM(E28:I28) -> 0
A29: 215以成本衡量之金融負債－流動 | C29: 2151 | D29: 以成本衡量之金融負債－流動 | E29: 0 | F29: 0 | G29: 0 | H29: =E29-F29 -> 0 | I29: =F29-G29 -> 0 | J29: =SUM(E29:I29) -> 0
A30: 215以成本衡量之金融負債－流動 | B30: 215 | D30: 以成本衡量之金融負債－流動 | E30: =SUBTOTAL(9,E29:E29) -> 0 | F30: =SUBTOTAL(9,F29:F29) -> 0 | G30: =SUBTOTAL(9,G29:G29) -> 0 | H30: =SUBTOTAL(9,H29:H29) -> 0 | I30: =SUBTOTAL(9,I29:I29) -> 0 | J30: =SUM(E30:I30) -> 0
A31: 216應付票據 | C31: 2161 | D31: 應付票據 | E31: 0 | F31: 0 | G31: 0 | H31: =E31-F31 -> 0 | I31: =F31-G31 -> 0 | J31: =SUM(E31:I31) -> 0
A32: 216應付票據 | C32: 2162 | D32: 應付票據—關係人 | E32: 0 | F32: 0 | G32: 0 | H32: =E32-F32 -> 0 | I32: =F32-G32 -> 0 | J32: =SUM(E32:I32) -> 0
A33: 216應付票據 | C33: 2163 | D33: 其他應付票據 | E33: 0 | F33: 0 | G33: 0 | H33: =E33-F33 -> 0 | I33: =F33-G33 -> 0 | J33: =SUM(E33:I33) -> 0
A34: 216應付票據 | B34: 216 | D34: 應付票據 | E34: =SUBTOTAL(9,E31:E33) -> 0 | F34: =SUBTOTAL(9,F31:F33) -> 0 | G34: =SUBTOTAL(9,G31:G33) -> 0 | H34: =SUBTOTAL(9,H31:H33) -> 0 | I34: =SUBTOTAL(9,I31:I33) -> 0 | J34: =SUM(E34:I34) -> 0
A35: 217應付帳款 | C35: 2171 | D35: 應付帳款 | E35: 0 | F35: 0 | G35: 0 | H35: =E35-F35 -> 0 | I35: =F35-G35 -> 0 | J35: =SUM(E35:I35) -> 0
A36: 217應付帳款 | C36: 2172 | D36: 應付租賃款—流動 | E36: 0 | F36: 0 | G36: 0 | H36: =E36-F36 -> 0 | I36: =F36-G36 -> 0 | J36: =SUM(E36:I36) -> 0
A37: 217應付帳款 | C37: 2173 | D37: 應付帳款—關係人 | E37: 0 | F37: 0 | G37: 0 | H37: =E37-F37 -> 0 | I37: =F37-G37 -> 0 | J37: =SUM(E37:I37) -> 0
A38: 217應付帳款 | B38: 217 | D38: 應付帳款 | E38: =SUBTOTAL(9,E35:E37) -> 0 | F38: =SUBTOTAL(9,F35:F37) -> 0 | G38: =SUBTOTAL(9,G35:G37) -> 0 | H38: =SUBTOTAL(9,H35:H37) -> 0 | I38: =SUBTOTAL(9,I35:I37) -> 0 | J38: =SUM(E38:I38) -> 0
A39: 218 應付建造合約款 | C39: 218 | D39: 應付建造合約款 | E39: 0 | F39: 0 | G39: 0 | H39: =E39-F39 -> 0 | I39: =F39-G39 -> 0 | J39: =SUM(E39:I39) -> 0
A40: 218應付建造合約款 | B40: 218 | D40: 應付建造合約款 | E40: =SUBTOTAL(9,E39) -> 0 | F40: =SUBTOTAL(9,F39) -> 0 | G40: =SUBTOTAL(9,G39) -> 0 | H40: =SUBTOTAL(9,H39) -> 0 | I40: =SUBTOTAL(9,I39) -> 0 | J40: =SUM(E40:I40) -> 0
A41: 219-220其他應付款 | C41: 2191 | D41: 應付薪資 | E41: 0 | F41: 0 | G41: 0 | H41: =E41-F41 -> 0 | I41: =F41-G41 -> 0 | J41: =SUM(E41:I41) -> 0
A42: 219-220其他應付款 | C42: 2192 | D42: 應付租金 | E42: 0 | F42: 0 | G42: 0 | H42: =E42-F42 -> 0 | I42: =F42-G42 -> 0 | J42: =SUM(E42:I42) -> 0
A43: 219-220其他應付款 | C43: 2193 | D43: 應付利息 | E43: 0 | F43: 0 | G43: 0 | H43: =E43-F43 -> 0 | I43: =F43-G43 -> 0 | J43: =SUM(E43:I43) -> 0
A44: 219-220其他應付款 | C44: 2194 | D44: 應付營業稅 | E44: 0 | F44: 0 | G44: 0 | H44: =E44-F44 -> 0 | I44: =F44-G44 -> 0 | J44: =SUM(E44:I44) -> 0
A45: 219-220其他應付款 | C45: 2195 | D45: 應付稅捐—其他 | E45: 0 | F45: 0 | G45: 0 | H45: =E45-F45 -> 0 | I45: =F45-G45 -> 0 | J45: =SUM(E45:I45) -> 0
A46: 219-220其他應付款 | C46: 2196 | D46: 應付退休金費用 | E46: 0 | F46: 0 | G46: 0 | H46: =E46-F46 -> 0 | I46: =F46-G46 -> 0 | J46: =SUM(E46:I46) -> 0
A47: 219-220其他應付款 | C47: 2197 | D47: 其他應付費用 | E47: 0 | F47: 0 | G47: 0 | H47: =E47-F47 -> 0 | I47: =F47-G47 -> 0 | J47: =SUM(E47:I47) -> 0
A48: 219-220其他應付款 | C48: 2198 | D48: 應付土地房屋款 | E48: 0 | F48: 0 | G48: 0 | H48: =E48-F48 -> 0 | I48: =F48-G48 -> 0 | J48: =SUM(E48:I48) -> 0
A49: 219-220其他應付款 | C49: 2199 | D49: 應付設備款 | E49: 0 | F49: 0 | G49: 0 | H49: =E49-F49 -> 0 | I49: =F49-G49 -> 0 | J49: =SUM(E49:I49) -> 0
A50: 219-220其他應付款 | C50: 2200 | D50: 其他應付款—關係人 | E50: 0 | F50: 0 | G50: 0 | H50: =E50-F50 -> 0 | I50: =F50-G50 -> 0 | J50: =SUM(E50:I50) -> 0
A51: 219-220其他應付款 | C51: 2201 | D51: 應付股利 | E51: 0 | F51: 0 | G51: 0 | H51: =E51-F51 -> 0 | I51: =F51-G51 -> 0 | J51: =SUM(E51:I51) -> 0
A52: 219-220其他應付款 | C52: 2202 | D52: 應付員工酬勞 | E52: 0 | F52: 0 | G52: 0 | H52: =E52-F52 -> 0 | I52: =F52-G52 -> 0 | J52: =SUM(E52:I52) -> 0
... A54: 219-220其他應付款 | C54: 2204 | D54: 銷項稅額 | E54: 0 | F54: 0 | G54: 0 | H54: =E54-F54 -> 0 | I54: =F54-G54 -> 0 | J54: =SUM(E54:I54) -> 0
A55: 219-220其他應付款 | B55: 219-220 | D55: 其他應付款 | E55: =SUBTOTAL(9,E41:E54) -> 0 | F55: =SUBTOTAL(9,F41:F54) -> 0 | G55: =SUBTOTAL(9,G41:G54) -> 0 | H55: =SUBTOTAL(9,H41:H54) -> 0 | I55: =SUBTOTAL(9,I41:I54) -> 0 | J55: =SUM(E55:I55) -> 0
A56: 221本期所得稅負債 | C56: 2211 | D56: 本期所得稅負債 | E56: 0 | F56: 0 | G56: 0 | H56: =E56-F56 -> 0 | I56: =F56-G56 -> 0 | J56: =SUM(E56:I56) -> 0
A57: 221本期所得稅負債 | B57: 221 | D57: 本期所得稅負債 | E57: =SUBTOTAL(9,E56:E56) -> 0 | F57: =SUBTOTAL(9,F56:F56) -> 0 | G57: =SUBTOTAL(9,G56:G56) -> 0 | H57: =SUBTOTAL(9,H56:H56) -> 0 | I57: =SUBTOTAL(9,I56:I56) -> 0 | J57: =SUM(E57:I57) -> 0
A58: 222預收款項 | C58: 2221 | D58: 預收貨款 | E58: 0 | F58: 0 | G58: 0 | H58: =E58-F58 -> 0 | I58: =F58-G58 -> 0 | J58: =SUM(E58:I58) -> 0
A59: 222預收款項 | C59: 2222 | D59: 預收收入 | E59: 0 | F59: 0 | G59: 0 | H59: =E59-F59 -> 0 | I59: =F59-G59 -> 0 | J59: =SUM(E59:I59) -> 0
A60: 222預收款項 | C60: 2223 | D60: 其他預收款 | E60: 0 | F60: 0 | G60: 0 | H60: =E60-F60 -> 0 | I60: =F60-G60 -> 0 | J60: =SUM(E60:I60) -> 0
A61: 222預收款項 | B61: 222 | D61: 預收款項 | E61: =SUBTOTAL(9,E58:E60) -> 0 | F61: =SUBTOTAL(9,F58:F60) -> 0 | G61: =SUBTOTAL(9,G58:G60) -> 0 | H61: =SUBTOTAL(9,H58:H60) -> 0 | I61: =SUBTOTAL(9,I58:I60) -> 0 | J61: =SUM(E61:I61) -> 0
A62: 223一年內到期長期負債 | C62: 2231 | D62: 一年內到期應付公司債 | E62: 0 | F62: 0 | G62: 0 | H62: =E62-F62 -> 0 | I62: =F62-G62 -> 0 | J62: =SUM(E62:I62) -> 0
A63: 223一年內到期長期負債 | C63: 2232 | D63: 一年內到期長期借款 | E63: 0 | F63: 0 | G63: 0 | H63: =E63-F63 -> 0 | I63: =F63-G63 -> 0 | J63: =SUM(E63:I63) -> 0
A64: 223一年內到期長期負債 | C64: 2233 | D64: 一年內到期長期應付票據及款項 | E64: 0 | F64: 0 | G64: 0 | H64: =E64-F64 -> 0 | I64: =F64-G64 -> 0 | J64: =SUM(E64:I64) -> 0
A65: 223一年內到期長期負債 | C65: 2234 | D65: 一年內到期長期應付票據及款項—關係人 | E65: 0 | F65: 0 | G65: 0 | H65: =E65-F65 -> 0 | I65: =F65-G65 -> 0 | J65: =SUM(E65:I65) -> 0
A66: 223一年內到期長期負債 | C66: 2235 | D66: 一年內到期其他長期負債 | E66: 0 | F66: 0 | G66: 0 | H66: =E66-F66 -> 0 | I66: =F66-G66 -> 0 | J66: =SUM(E66:I66) -> 0
A67: 223一年內到期長期負債 | B67: 223 | D67: 一年內到期長期負債 | E67: =SUBTOTAL(9,E62:E66) -> 0 | F67: =SUBTOTAL(9,F62:F66) -> 0 | G67: =SUBTOTAL(9,G62:G66) -> 0 | H67: =SUBTOTAL(9,H62:H66) -> 0 | I67: =SUBTOTAL(9,I62:I66) -> 0 | J67: =SUM(E67:I67) -> 0
A68: 224負債準備—流動 | C68: 2241 | D68: 售後服務—保固負債準備 | E68: 0 | F68: 0 | G68: 0 | H68: =E68-F68 -> 0 | I68: =F68-G68 -> 0 | J68: =SUM(E68:I68) -> 0
A69: 224負債準備—流動 | C69: 2242 | D69: 虧損性合約之短期負債準備 | E69: 0 | F69: 0 | G69: 0 | H69: =E69-F69 -> 0 | I69: =F69-G69 -> 0 | J69: =SUM(E69:I69) -> 0
A70: 224負債準備—流動 | C70: 2243 | D70: 除役、復原及修復成本之短期負債準備 | E70: 0 | F70: 0 | G70: 0 | H70: =E70-F70 -> 0 | I70: =F70-G70 -> 0 | J70: =SUM(E70:I70) -> 0
A71: 224負債準備—流動 | C71: 2244 | D71: 保證合約之短期負債準備 | E71: 0 | F71: 0 | G71: 0 | H71: =E71-F71 -> 0 | I71: =F71-G71 -> 0 | J71: =SUM(E71:I71) -> 0
A72: 224負債準備—流動 | C72: 2245 | D72: 銷貨退回及折讓之短期負債準備 | E72: 0 | F72: 0 | G72: 0 | H72: =E72-F72 -> 0 | I72: =F72-G72 -> 0 | J72: =SUM(E72:I72) -> 0
A73: 224負債準備—流動 | B73: 224 | D73: 負債準備—流動 | E73: =SUBTOTAL(9,E68:E72) -> 0 | F73: =SUBTOTAL(9,F68:F72) -> 0 | G73: =SUBTOTAL(9,G68:G72) -> 0 | H73: =SUBTOTAL(9,H68:H72) -> 0 | I73: =SUBTOTAL(9,I68:I72) -> 0 | J73: =SUM(E73:I73) -> 0
A74: 225其他流動負債 | C74: 2251 | D74: 暫收款 | E74: 0 | F74: 0 | G74: 0 | H74: =E74-F74 -> 0 | I74: =F74-G74 -> 0 | J74: =SUM(E74:I74) -> 0
A75: 225其他流動負債 | C75: 2252 | D75: 代收款 | E75: 0 | F75: 0 | G75: 0 | H75: =E75-F75 -> 0 | I75: =F75-G75 -> 0 | J75: =SUM(E75:I75) -> 0
A76: 225其他流動負債 | B76: 225 | D76: 其他流動負債 | E76: =SUBTOTAL(9,E74:E75) -> 0 | F76: =SUBTOTAL(9,F74:F75) -> 0 | G76: =SUBTOTAL(9,G74:G75) -> 0 | H76: =SUBTOTAL(9,H74:H75) -> 0 | I76: =SUBTOTAL(9,I74:I75) -> 0 | J76: =SUM(E76:I76) -> 0
D77: 非流動負債 | E77: 0 | F77: 0 | G77: 0 | H77: =E77-F77 -> 0 | I77: =F77-G77 -> 0 | J77: =SUM(E77:I77) -> 0
A78: 231透過損益按公允價值衡量之金融負債－非流動 | C78: 2311 | D78: 透過損益按公允價值衡量之金融負債－非流動 | E78: 0 | F78: 0 | G78: 0 | H78: =E78-F78 -> 0 | I78: =F78-G78 -> 0 | J78: =SUM(E78:I78) -> 0
A79: 231透過損益按公允價值衡量之金融負債－非流動 | C79: 2312 | D79: 透過損益按公允價值衡量之金融負債評價調整—非流動 | E79: 0 | F79: 0 | G79: 0 | H79: =E79-F79 -> 0 | I79: =F79-G79 -> 0 | J79: =SUM(E79:I79) -> 0
A80: 231透過損益按公允價值衡量之金融負債－非流動 | B80: 231 | D80: 透過損益按公允價值衡量之金融負債－非流動 | E80: =SUBTOTAL(9,E78:E79) -> 0 | F80: =SUBTOTAL(9,F78:F79) -> 0 | G80: =SUBTOTAL(9,G78:G79) -> 0 | H80: =SUBTOTAL(9,H78:H79) -> 0 | I80: =SUBTOTAL(9,I78:I79) -> 0 | J80: =SUM(E80:I80) -> 0
A81: 232避險之衍生金融負債—非流動 | C81: 2321 | D81: 避險之衍生金融負債—非流動 | E81: 0 | F81: 0 | G81: 0 | H81: =E81-F81 -> 0 | I81: =F81-G81 -> 0 | J81: =SUM(E81:I81) -> 0
A82: 232避險之衍生金融負債—非流動 | C82: 2322 | D82: 避險之衍生金融負債評價調整—非流動 | E82: 0 | F82: 0 | G82: 0 | H82: =E82-F82 -> 0 | I82: =F82-G82 -> 0 | J82: =SUM(E82:I82) -> 0
A83: 232避險之衍生金融負債—非流動 | B83: 232 | D83: 避險之衍生金融負債—非流動 | E83: =SUBTOTAL(9,E81:E82) -> 0 | F83: =SUBTOTAL(9,F81:F82) -> 0 | G83: =SUBTOTAL(9,G81:G82) -> 0 | H83: =SUBTOTAL(9,H81:H82) -> 0 | I83: =SUBTOTAL(9,I81:I82) -> 0 | J83: =SUM(E83:I83) -> 0
A84: 233以成本衡量之金融負債－非流動 | C84: 2331 | D84: 以成本衡量之金融負債－非流動 | E84: 0 | F84: 0 | G84: 0 | H84: =E84-F84 -> 0 | I84: =F84-G84 -> 0 | J84: =SUM(E84:I84) -> 0
A85: 233以成本衡量之金融負債－非流動 | B85: 233 | D85: 以成本衡量之金融負債－非流動 | E85: =SUBTOTAL(9,E84:E84) -> 0 | F85: =SUBTOTAL(9,F84:F84) -> 0 | G85: =SUBTOTAL(9,G84:G84) -> 0 | H85: =SUBTOTAL(9,H84:H84) -> 0 | I85: =SUBTOTAL(9,I84:I84) -> 0 | J85: =SUM(E85:I85) -> 0
A86: 234應付公司債 | C86: 2341 | D86: 應付公司債 | E86: 0 | F86: 0 | G86: 0 | H86: =E86-F86 -> 0 | I86: =F86-G86 -> 0 | J86: =SUM(E86:I86) -> 0
A87: 234應付公司債 | C87: 2342 | D87: 應付公司債溢(折)價 | E87: 0 | F87: 0 | G87: 0 | H87: =E87-F87 -> 0 | I87: =F87-G87 -> 0 | J87: =SUM(E87:I87) -> 0
A88: 234應付公司債 | B88: 234 | D88: 應付公司債 | E88: =SUBTOTAL(9,E86:E87) -> 0 | F88: =SUBTOTAL(9,F86:F87) -> 0 | G88: =SUBTOTAL(9,G86:G87) -> 0 | H88: =SUBTOTAL(9,H86:H87) -> 0 | I88: =SUBTOTAL(9,I86:I87) -> 0 | J88: =SUM(E88:I88) -> 0
A89: 235長期借款 | C89: 2351 | D89: 長期銀行借款 | E89: 0 | F89: 0 | G89: 0 | H89: =E89-F89 -> 0 | I89: =F89-G89 -> 0 | J89: =SUM(E89:I89) -> 0
A90: 235長期借款 | C90: 2352 | D90: 長期借款—業主 | E90: 0 | F90: 0 | G90: 0 | H90: =E90-F90 -> 0 | I90: =F90-G90 -> 0 | J90: =SUM(E90:I90) -> 0
A91: 235長期借款 | C91: 2353 | D91: 長期借款—員工 | E91: 0 | F91: 0 | G91: 0 | H91: =E91-F91 -> 0 | I91: =F91-G91 -> 0 | J91: =SUM(E91:I91) -> 0
A92: 235長期借款 | C92: 2354 | D92: 長期借款—關係人 | E92: 0 | F92: 0 | G92: 0 | H92: =E92-F92 -> 0 | I92: =F92-G92 -> 0 | J92: =SUM(E92:I92) -> 0
A93: 235長期借款 | C93: 2355 | D93: 長期借款—其他 | E93: 0 | F93: 0 | G93: 0 | H93: =E93-F93 -> 0 | I93: =F93-G93 -> 0 | J93: =SUM(E93:I93) -> 0
A94: 235長期借款 | B94: 235 | D94: 長期借款 | E94: =SUBTOTAL(9,E89:E93) -> 0 | F94: =SUBTOTAL(9,F89:F93) -> 0 | G94: =SUBTOTAL(9,G89:G93) -> 0 | H94: =SUBTOTAL(9,H89:H93) -> 0 | I94: =SUBTOTAL(9,I89:I93) -> 0 | J94: =SUM(E94:I94) -> 0
A95: 236長期應付票據及款項 | C95: 2361 | D95: 長期應付票據 | E95: 0 | F95: 0 | G95: 0 | H95: =E95-F95 -> 0 | I95: =F95-G95 -> 0 | J95: =SUM(E95:I95) -> 0
A96: 236長期應付票據及款項 | C96: 2362 | D96: 長期應付帳款 | E96: 0 | F96: 0 | G96: 0 | H96: =E96-F96 -> 0 | I96: =F96-G96 -> 0 | J96: =SUM(E96:I96) -> 0
A97: 236長期應付票據及款項 | C97: 2363 | D97: 長期租賃款-非流動 | E97: 0 | F97: 0 | G97: 0 | H97: =E97-F97 -> 0 | I97: =F97-G97 -> 0 | J97: =SUM(E97:I97) -> 0
A98: 236長期應付票據及款項 | C98: 2364 | D98: 長期應付票據及款項—關係人 | E98: 0 | F98: 0 | G98: 0 | H98: =E98-F98 -> 0 | I98: =F98-G98 -> 0 | J98: =SUM(E98:I98) -> 0
A99: 236長期應付票據及款項 | C99: 2365 | D99: 其他長期應付款項 | E99: 0 | F99: 0 | G99: 0 | H99: =E99-F99 -> 0 | I99: =F99-G99 -> 0 | J99: =SUM(E99:I99) -> 0
A100: 236長期應付票據及款項 | B100: 236 | D100: 長期應付票據及款項 | E100: =SUBTOTAL(9,E95:E99) -> 0 | F100: =SUBTOTAL(9,F95:F99) -> 0 | G100: =SUBTOTAL(9,G95:G99) -> 0 | H100: =SUBTOTAL(9,H95:H99) -> 0 | I100: =SUBTOTAL(9,I95:I99) -> 0 | J100: =SUM(E100:I100) -> 0
A101: 237負債準備—非流動 | C101: 2371 | D101: 虧損性合約之長期負債準備 | E101: 0 | F101: 0 | G101: 0 | H101: =E101-F101 -> 0 | I101: =F101-G101 -> 0 | J101: =SUM(E101:I101) -> 0
...

Sheet 104
A1: 資 產 | E1: 負債及股東權益
A2: 流動資產 | E2: 流動負債
A3: 現 金(附註二及三) | B3: 151815693 | C3: 82230452 | D3: =C3-B3 -> -69585241 | E3: 短期借款(附註三及五) | F3: 173539562 | G3: 96436082 | H3: =F3-G3 -> 77103480
A4: 應收票據(附註二) | B4: 169428468 | C4: 265863605 | D4: =C4-B4 -> 96435137 | E4: 應付票據 | F4: 56169952 | G4: 173201636 | H4: =F4-G4 -> -117031684
A5: 應收帳款(附註二) | B5: 291114741 | C5: 364529240 | D5: =C5-B5 -> 73414499 | E5: 應付帳款 | F5: 24391813 | G5: 107020814 | H5: =F5-G5 -> -82629001
A6: 存 貨（附註二及三） | B6: 430305453 | C6: 428681929 | D6: =C6-B6 -> -1623524 | E6: 應付費用 | F6: 18608615 | G6: 23943919 | H6: =F6-G6 -> -5335304
A7: 預付款項 | B7: 3131465 | C7: 7013896 | D7: =C7-B7 -> 3882431 | E7: 應付所得稅(附註二及三) | F7: 9697468 | G7: 15156447 | H7: =F7-G7 -> -5458979
A8: 其他流動資產(附註五) | B8: 17767045 | C8: 7305927 | D8: =C8-B8 -> -10461118 | E8: 一年內到期之長期借款 | F8: 64660733 | G8: 33436447 | H8: =F8-G8 -> 31224286
A9: 流動資產合計 | B9: =SUM(B3:B8) -> 1063562865 | C9: =SUM(C3:C8) -> 1155625049 | D9: =C9-B9 -> 92062184 | E9: (附註三及五) | H9: =F9-G9 -> 0
D10: =C10-B10 -> 0 | E10: 預收款項 | F10: 1243844 | G10: 371510 | H10: =F10-G10 -> 872334
A11: 基金及投資(附註一、二及三) | D11: =C11-B11 -> 0 | E11: 遞延所得稅負債-流動(附註二及三) | F11: 258557 | G11: 1578922 | H11: =F11-G11 -> -1320365
A12: 採權益法之長期股權投資 | B12: 6752501 | C12: 6065643 | D12: =C12-B12 -> -686858 | E12: 其他流動負債 | F12: 1116703 | G12: 1328967 | H12: =F12-G12 -> -212264
D13: =C13-B13 -> 0 | E13: 流動負債合計 | F13: =SUM(F3:F12) -> 349687247 | G13: =SUM(G3:G12) -> 452474744 | H13: =F13-G13 -> -102787497
A14: 固定資產(附註二、三、四、五及六) | D14: =C14-B14 -> 0 | H14: =F14-G14 -> 0
A15: 成 本 | D15: =C15-B15 -> 0 | E15: 長期負債 | H15: =F15-G15 -> 0
A16: 土 地 | B16: 288310086 | C16: 288310086 | D16: =C16-B16 -> 0 | E16: 長期借款(附註三及五) | F16: 904465360 | G16: 797736642 | H16: =F16-G16 -> 106728718
A17: 房屋及建築 | B17: 55599774 | C17: 51411864 | D17: =C17-B17 -> -4187910 | H17: =F17-G17 -> 0
A18: 機器設備 | B18: 608133599 | C18: 467217879 | D18: =C18-B18 -> -140915720 | E18: 負債總計 | F18: =F13+F16 -> 1254152607 | G18: =G13+G16 -> 1250211386 | H18: =F18-G18 -> 3941221
A19: 運輸設備 | B19: 2086822 | C19: 1656822 | D19: =C19-B19 -> -430000 | H19: =F19-G19 -> 0
A20: 辦公設備 | B20: 22974040 | C20: 21722896 | D20: =C20-B20 -> -1251144 | H20: =F20-G20 -> 0
A21: 其他固定資產 | B21: 14442877 | C21: 13926463 | D21: =C21-B21 -> -516414 | H21: =F21-G21 -> 0
B22: =SUM(B16:B21) -> 991547198 | C22: =SUM(C16:C21) -> 844246010 | D22: =C22-B22 -> -147301188 | E22: 股東權益 | H22: =F22-G22 -> 0
A23: 減：累計折舊 | B23: 221642030 | C23: 168259127 | D23: =C23-B23 -> -53382903 | E23: 股 本(附註一及三) | F23: 304980000 | G23: 304980000 | H23: =F23-G23 -> 0
A24: 未完工程及待驗設備 | B24: 3219825 | C24: 0 | D24: =C24-B24 -> -3219825 | E24: 資本公積(附註三) | F24: 57460000 | G24: 57460000 | H24: =F24-G24 -> 0
A25: 預付設備款 | B25: 6473 | C25: 6039 | D25: =C25-B25 -> -434 | E25: 保留盈餘(附註三) | H25: =F25-G25 -> 0
A26: 固定資產淨額 | B26: =B22-B23+B24+B25 -> 773131466 | C26: =C22-C23+C25 -> 675992922 | D26: =C26-B26 -> -97138544 | E26: 法定盈餘公積 | F26: =2656286+37016938 -> 39673224 | G26: =2656286+25862198 -> 28518484 | H26: =F26-G26 -> 11154740
D27: =C27-B27 -> 0 | E27: 未分配盈餘 | F27: =10906569+122890325+70518488 -> 204315382 | G27: =10906569+83470175+111547401 -> 205924145 | H27: =F27-G27 -> -1608763
A28: 其他非流動資產 | D28: =C28-B28 -> 0 | E28: 股東權益總計 | F28: =SUM(F23:F27) -> 606428606 | G28: =SUM(G23:G27) -> 596882629 | H28: =F28-G28 -> 9545977
A29: 存出保證金(附註五) | B29: 9882662 | C29: 4254001 | D29: =C29-B29 -> -5628661 | H29: =F29-G29 -> 0
A30: 未攤銷費用(附註二) | B30: 7251719 | C30: 5156400 | D30: =C30-B30 -> -2095319 | H30: =F30-G30 -> 0
A31: 其他資產合計 | B31: =SUM(B29:B30) -> 17134381 | C31: =SUM(C29:C30) -> 9410401 | D31: =C31-B31 -> -7723980 | H31: =F31-G31 -> 0
D32: =C32-B32 -> 0 | H32: =F32-G32 -> 0
A33: 資 產 總 計 | B33: =B9+B12+B26+B31 -> 1860581213 | C33: =C9+C12+C26+C31 -> 1847094015 | E33: 負債及股東權益總計 | F33: =F18+F28 -> 1860581213 | G33: =G18+G28 -> 1847094015
A37: 負 責 人：
B38: 288310086 | C38: － | D38: ) | E38: $ | F38: 288310086
B39: 55599774 | C39: 23598255 | D39: ) | F39: =B39-C39 -> 32001519
B40: 608133599 | C40: 172357639 | D40: ) | F40: =B40-C40 -> 435775960
B41: 2086822 | C41: 1243704 | D41: ) | F41: =B41-C41 -> 843118
B42: 22974040 | C42: 13576662 | D42: ) | F42: =B42-C42 -> 9397378
B43: 14442877 | C43: 10865770 | D43: ) | F43: =B43-C43 -> 3577107
B44: 3219825 | C44: — | D44: ) | F44: =B44 -> 3219825
B45: 6473 | C45: — | F45: =B45 -> 6473
B46: 994773496 | C46: 221642030 | D46: ) | E46: $ | F46: =B46-C46 -> 773131466

Sheet 首次企業項目差異
A1: 本公司係依循企業會計準則公報第二號第二十二第二項之作法轉換至企業會計準則公報，因此揭露與先前適用之一般公認會計原則間之重大差異如下:
A2: 民國一○四年十二月三十一日資產負債表項目之調節表
A4: 先前一般公認會計原則 | E4: 轉換之影響 | G4: 企業會計準則公報
A5: 項目 | C5: 金額 | E5: 表達差異 | G5: 金額 | I5: 項目 | K5: 註
A6: 流動資產 | I6: 流動資產
A7: 現金及約當現金 | I7: 現金及約當現金 | K7: 1
A8: 公平價值變動列入損益之金融資產-流動 | I8: 透過損益按公允價值衡量之金融資產-流動 | K8: 2
A9: 備供出售金融資產-流動 | I9: 備供出售金融資產-流動
A10: 持有至到期日金融資產-流動 | I10: 持有至到期日金融資產-流動
A11: 避險之衍生性金融資產-流動 | I11: 避險之衍生金融資產-流動
A12: 以成本衡量之金融資產-流動 | I12: 以成本衡量之金融資產-流動 | K12: 2
A13: 無活絡市場之債券投資-流動 | I13: 無活絡市場之債券投資-流動 | K13: 1
A14: 應收票據 | I14: 應收票據
A15: 應收帳款 | I15: 應收帳款
A16: 其他應收款 | I16: 其他應收款
A17: - | I17: 當期所得稅資產
A18: 存貨 | I18: 存貨
A19: - | I19: 生物資產-流動
A20: 在建工程 | I20: 在建工程
A21: 預付款項 | I21: 預付款項 | K21: 3,5
A22: 遞延所得稅資產 | I22: - | K22: 7
A23: 待出售非流動資產 | I23: 待出售非流動資產
A24: 其他流動資產 | I24: 其他流動資產
A25: 流動資產合計 | I25: 流動資產合計
A27: 基金及投資 | I27: 非流動資產
A28: 公平價值變動列入損益之金融資產-非流動 | I28: 透過損益按公允價值衡量之金融資產-非流動
A29: 備供出售金融資產-非流動 | I29: 備供出售金融資產-非流動 | K29: 2
A30: 持有至到期日金融資產-非流動 | I30: 持有至到期日金融資產-非流動
A31: 避險之衍生性金融資產-非流動 | I31: 避險之衍生金融資產-非流動
A32: 以成本衡量之金融資產-非流動 | I32: 以成本衡量之金融資產-非流動 | K32: 2
A33: 無活絡市場之債券投資-非流動 | I33: 無活絡市場之債券投資-非流動
A34: 償債基金 | I34: 償債基金
A35: 採權益法之長期股權投資 | I35: 採權益法之投資
A36: 其他金融資產 | I36: 其他金融資產
A39: 固定資產淨額 | I39: 不動產、廠房及設備 | K39: 5
A40: - | I40: 投資性不動產 | K40: 4
A42: 無形資產合計 | I42: 無形資產 | K42: 3
A43: - | I43: 生物資產-非流動
I45: 預付設備款
A47: 其他資產
A48: 出租資產 | I48: - | K48: 4
A49: 閒置資產 | I49: - | K49: 4
A50: - | I50: 長期預付租金 | K50: 3
A51: 存出保證金 | I51: 存出保證金
A52: 遞延所得稅資產 | I52: 遞延所得稅資產 | K52: 7
A54: 資產總計 | I54: 資產總計
A57: 先前一般公認會計原則 | E57: 轉換之影響 | G57: 企業會計準則公報
A58: 項目 | C58: 金額 | E58: 表達差異 | G58: 金額 | H58: 項目 | J58: 註
A59: 流動負債 | H59: 流動負債
A60: 短期借款 | H60: 短期借款
A61: 應付短期票券 | H61: 應付短期票券
A62: 公平價值變動列入損益之金融負債-流動 | H62: 透過損益按公允價值衡量之金融負債-流動
A63: 避險之衍生性金融負債-流動 | H63: 避險之衍生金融負債-流動
A64: 以成本衡量之金融負債-流動 | H64: 以成本衡量之金融負債-流動
A65: 特別股負債-流動 | H65: 特別股負債-流動
A66: 應付票據 | H66: 應付票據
A67: 應付帳款 | H67: 應付帳款
A68: 應付所得稅 | H68: 當期所得稅負債
A69: 其他應付款 | H69: 其他應付款
A70: 其他金融負債 | H70: 其他金融負債
... A75: - | H75: 重組之短期負債準備
A76: 遞延所得稅負債 | H76: - | J76: 7
A77: 應付租賃款-流動 | H77: 應付租賃款-流動
A78: 與待出售非流動資產直接相關之負債 | H78: 與待出售非流動資產直接相關之負債
A79: 其他流動負債 | H79: 其他流動負債
A81: 長期負債 | H81: 非流動負債
A82: 公平價值變動列入損益之金融負債-非流動 | H82: 透過損益按公允價值衡量之金融負債-非流動
A83: 避險之衍生性金融資產-非流動 | H83: 避險之衍生金融負債-非流動
A84: 以成本衡量之金融負債-非流動 | H84: 以成本衡量之金融負債-非流動
A85: 應付公司債 | H85: 應付公司債
A86: 長期借款 | H86: 長期借款
A87: 應付租賃款-非流動 | H87: 應付租賃款-非流動
A88: 特別股負債-非流動 | H88: 特別股負債-非流動
A89: - | H89: 保固之長期負債準備
... A92: 其他金融負債 | H92: 其他金融負債
A94: 其他負債
A95: 存入保證金 | H95: 存入保證金
A96: 遞延所得稅負債 | H96: 遞延所得稅負債 | J96: 7
A98: 負債總計 | H98: 負債總計
A100: 股本 | H100: 股本
A101: 普通股股本 | H101: 普通股股本
A102: 特別股股本 | H102: 特別股股本
A103: 資本公積 | H103: 資本公積
A104: 保留盈餘 | H104: 保留盈餘
A105: 法定盈餘公積 | H105: 法定盈餘公積
A106: 特別盈餘公積 | H106: 特別盈餘公積
A107: 未分配盈餘 | H107: 未分配盈餘
A108: 股東權益其他項目 | H108: 其他權益
A109: 未實現重估增值 | H109: 未實現重估增值
A110: 備供出售金融資產未實現損益 | H110: 備供出售金融資產未實現損益
... A115: 負債及股東權益總計 | H115: 負債及權益總計
A117: 民國一○四年度綜合損益表項目之調節
A119: 先前一般公認會計原則 | E119: 轉換之影響 | G119: 企業會計準則公報
A120: 項目 | C120: 金額 | E120: 表達差異 | G120: 金額 | H120: 項目 | J120: 註
A122: 營業收入淨額 | H122: 營業收入淨額
A123: 營業成本 | H123: 營業成本
A124: 營業毛利 | H124: 營業毛利
A125: 營業費用 | H125: 營業費用
A126: 研究發展費用 | H126: 研發費用
A127: 管理費用 | H127: 管理費用
...
